Workbook

Sheet 统计概览
A2: 稳定币安全事件统计 | B2: 稳定币安全事件统计（v3.1） | C2: 稳定币安全事件统计（v3.1） | D2: 稳定币安全事件统计（v3.1） | E2: 稳定币安全事件统计（v3.1）
A3: 样本：108起事件；每起事件记录一个主要风险起点和一个主要风险性质。
A4: 风险起点 | B4: 总数 | C4: 继承 | D4: 重塑 | E4: 特有
A5: C_VS 价值支撑 | B5: =SUM(C5:E5) -> 14 | C5: =COUNTIFS('108案详情'!$H$5:$H$112,"C_VS",'108案详情'!$K$5:$K$112,"继承风险") -> 0 | D5: =COUNTIFS('108案详情'!$H$5:$H$112,"C_VS",'108案详情'!$K$5:$K$112,"重塑风险") -> 0 | E5: =COUNTIFS('108案详情'!$H$5:$H$112,"C_VS",'108案详情'!$K$5:$K$112,"稳定币特有风险") -> 14
A6: C_PR 协议规则 | B6: =SUM(C6:E6) -> 9 | C6: =COUNTIFS('108案详情'!$H$5:$H$112,"C_PR",'108案详情'!$K$5:$K$112,"继承风险") -> 3 | D6: =COUNTIFS('108案详情'!$H$5:$H$112,"C_PR",'108案详情'!$K$5:$K$112,"重塑风险") -> 6 | E6: =COUNTIFS('108案详情'!$H$5:$H$112,"C_PR",'108案详情'!$K$5:$K$112,"稳定币特有风险") -> 0
A7: C_CI 合约实现 | B7: =SUM(C7:E7) -> 20 | C7: =COUNTIFS('108案详情'!$H$5:$H$112,"C_CI",'108案详情'!$K$5:$K$112,"继承风险") -> 5 | D7: =COUNTIFS('108案详情'!$H$5:$H$112,"C_CI",'108案详情'!$K$5:$K$112,"重塑风险") -> 15 | E7: =COUNTIFS('108案详情'!$H$5:$H$112,"C_CI",'108案详情'!$K$5:$K$112,"稳定币特有风险") -> 0
A8: C_RD 运行依赖 | B8: =SUM(C8:E8) -> 8 | C8: =COUNTIFS('108案详情'!$H$5:$H$112,"C_RD",'108案详情'!$K$5:$K$112,"继承风险") -> 0 | D8: =COUNTIFS('108案详情'!$H$5:$H$112,"C_RD",'108案详情'!$K$5:$K$112,"重塑风险") -> 8 | E8: =COUNTIFS('108案详情'!$H$5:$H$112,"C_RD",'108案详情'!$K$5:$K$112,"稳定币特有风险") -> 0
A9: M_LI 流动性 | B9: =SUM(C9:E9) -> 5 | C9: =COUNTIFS('108案详情'!$H$5:$H$112,"M_LI",'108案详情'!$K$5:$K$112,"继承风险") -> 1 | D9: =COUNTIFS('108案详情'!$H$5:$H$112,"M_LI",'108案详情'!$K$5:$K$112,"重塑风险") -> 3 | E9: =COUNTIFS('108案详情'!$H$5:$H$112,"M_LI",'108案详情'!$K$5:$K$112,"稳定币特有风险") -> 1
A10: M_PR 锚定修复 | B10: =SUM(C10:E10) -> 3 | C10: =COUNTIFS('108案详情'!$H$5:$H$112,"M_PR",'108案详情'!$K$5:$K$112,"继承风险") -> 0 | D10: =COUNTIFS('108案详情'!$H$5:$H$112,"M_PR",'108案详情'!$K$5:$K$112,"重塑风险") -> 0 | E10: =COUNTIFS('108案详情'!$H$5:$H$112,"M_PR",'108案详情'!$K$5:$K$112,"稳定币特有风险") -> 3
A11: M_CR 信心挤兑 | B11: =SUM(C11:E11) -> 2 | C11: =COUNTIFS('108案详情'!$H$5:$H$112,"M_CR",'108案详情'!$K$5:$K$112,"继承风险") -> 1 | D11: =COUNTIFS('108案详情'!$H$5:$H$112,"M_CR",'108案详情'!$K$5:$K$112,"重塑风险") -> 1 | E11: =COUNTIFS('108案详情'!$H$5:$H$112,"M_CR",'108案详情'!$K$5:$K$112,"稳定币特有风险") -> 0
A12: E_IN 外部集成 | B12: =SUM(C12:E12) -> 25 | C12: =COUNTIFS('108案详情'!$H$5:$H$112,"E_IN",'108案详情'!$K$5:$K$112,"继承风险") -> 18 | D12: =COUNTIFS('108案详情'!$H$5:$H$112,"E_IN",'108案详情'!$K$5:$K$112,"重塑风险") -> 7 | E12: =COUNTIFS('108案详情'!$H$5:$H$112,"E_IN",'108案详情'!$K$5:$K$112,"稳定币特有风险") -> 0
A13: E_IU 违法利用 | B13: =SUM(C13:E13) -> 15 | C13: =COUNTIFS('108案详情'!$H$5:$H$112,"E_IU",'108案详情'!$K$5:$K$112,"继承风险") -> 3 | D13: =COUNTIFS('108案详情'!$H$5:$H$112,"E_IU",'108案详情'!$K$5:$K$112,"重塑风险") -> 12 | E13: =COUNTIFS('108案详情'!$H$5:$H$112,"E_IU",'108案详情'!$K$5:$K$112,"稳定币特有风险") -> 0
A14: E_RJ 监管法域 | B14: =SUM(C14:E14) -> 7 | C14: =COUNTIFS('108案详情'!$H$5:$H$112,"E_RJ",'108案详情'!$K$5:$K$112,"继承风险") -> 0 | D14: =COUNTIFS('108案详情'!$H$5:$H$112,"E_RJ",'108案详情'!$K$5:$K$112,"重塑风险") -> 1 | E14: =COUNTIFS('108案详情'!$H$5:$H$112,"E_RJ",'108案详情'!$K$5:$K$112,"稳定币特有风险") -> 6
A15: 合计 | B15: =SUM(B5:B14) -> 108 | C15: =SUM(C5:C14) -> 31 | D15: =SUM(D5:D14) -> 53 | E15: =SUM(E5:E14) -> 24
A18: 分析空间
A19: 分析空间 | B19: 数量 | C19: 占全部事件
A20: 核心机制 | B20: =COUNTIF('108案详情'!$I$5:$I$112,A20) -> 51 | C20: =B20/$B$15 -> 0.47222222
A21: 市场运行 | B21: =COUNTIF('108案详情'!$I$5:$I$112,A21) -> 10 | C21: =B21/$B$15 -> 0.092592593
A22: 外部生态 | B22: =COUNTIF('108案详情'!$I$5:$I$112,A22) -> 47 | C22: =B22/$B$15 -> 0.43518519
A23: 合计 | B23: =SUM(B20:B22) -> 108 | C23: =SUM(C20:C22) -> 1
A26: 市场表现与传播
A27: 统计项目 | B27: 数量 | C27: 占全部事件
A28: 记录为脱锚 | B28: =COUNTIF('108案详情'!$N$5:$N$112,"是") -> 32 | C28: =B28/$B$15 -> 0.2962963
A29: 局部/短时价格偏离 | B29: =COUNTIF('108案详情'!$N$5:$N$112,"局部/短时") -> 12 | C29: =B29/$B$15 -> 0.11111111
A30: 至少一次跨空间传播 | B30: =$B$15-COUNTIF('108案详情'!$R$5:$R$112,"C")-COUNTIF('108案详情'!$R$5:$R$112,"M")-COUNTIF('108案详情'!$R$5:$R$112,"E") -> 45 | C30: =B30/$B$15 -> 0.41666667
A33: 分类说明
A34: 风险起点依据最先出现的关键风险条件；后续价格下跌、挤兑或损失不自动改变起点。
A35: 继承：去掉稳定价值目标后，风险在一般区块链或加密资产系统中仍然成立。
A36: 重塑：稳定价值目标或机制改变既有风险的触发条件、传播方式或影响范围。
A37: 特有：直接来自维持稳定价值所增加的资产支撑、兑付承诺、铸赎或稳定机制。
A38: 事件时间保留来源精度；区间、公告与披露时间按原记录展示。
A39: 资产证明用于识别资产；来源未明确事件链版本时，证明链接不代表事件发生链。

Sheet 108案详情
A2: 108起稳定币安全事件 | B2: 108起稳定币安全事件（v3.1勘误版） | C2: 108起稳定币安全事件（v3.1勘误版） | D2: 108起稳定币安全事件（v3.1勘误版）
A4: 序号 | B4: 事件时间 | C4: 事件名称 | D4: 稳定币/资产版本 | E4: 链/主要场景 | F4: 价值支撑方式 | G4: 稳定币角色 | H4: 风险起点 | I4: 风险空间 | J4: 风险类型 | K4: 风险性质 | L4: 首个关键风险条件 | M4: 事件过程 | N4: 价格偏离情况 | O4: 市场表现 | P4: 影响规模 | Q4: 处置结果 | R4: 传播空间序列 | S4: 证据限定 | T4: 事件依据 | U4: 资产证明
A5: 1 | B5: 2016-06-01—2019-02-25被调查陈述；2021-10-15命令 | C5: Tether：CFTC储备陈述执法和解 | D5: USDT | E5: Tether储备／银行体系 | F5: 法币储备型稳定币或其外部使用/处置场景 | G5: USDT是CFTC审查其储备支持陈述的稳定币 | H5: C_VS | I5: 核心机制 | J5: 核心机制—价值支撑风险 | K5: 稳定币特有风险 | L5: Tether在调查期内并非所有时点都以足额法币储备支持USDT，却作出充分储备相关陈述 | M5: 储备支持陈述与实际覆盖不一致 → 监管调查 → CFTC罚款4100万美元 → 储备披露治理加强 | N5: 否 | O5: USDT未以调查期脱锚作为核心结果；监管关注点是储备覆盖与对外陈述。 | P5: CFTC罚款4,100万美元；调查样本中仅27.6%的天数拥有足额法币储备 | Q5: Tether与CFTC和解并支付4,100万美元民事罚款，储备披露和构成随后加强 | R5: C→E | T5: 事件依据 | U5: 资产证明
A6: 2 | B6: 2017—2019相关行为；2021-02-23和解 | C6: Bitfinex／Tether：NYAG储备调查和解 | D6: USDT | E6: Bitfinex／Tether关联资金体系 | F6: 法币储备型稳定币或其外部使用/处置场景 | G6: USDT是储备与Bitfinex关联资金缺口相互耦合的稳定币 | H6: C_VS | I6: 核心机制 | J6: 核心机制—价值支撑风险 | K6: 稳定币特有风险 | L6: Bitfinex约8.5亿美元资金缺口通过Tether储备/关联交易安排获得流动性支持 | M6: Bitfinex资金缺口 → 动用/借用Tether相关储备流动性 → USDT储备独立性受质疑 → NYAG和解 | N6: 否 | O6: USDT未发生由该调查直接确认的持续脱锚；核心是储备独立性和关联方流动性风险。 | P6: Bitfinex约8.5亿美元资金缺口；与Tether达成1,850万美元和解并接受限制措施 | Q6: Bitfinex/Tether与纽约州总检察长达成1,850万美元和解并接受储备/交易限制及报告义务 | R6: C→E | T6: 事件依据 | U6: 资产证明
A7: 3 | B7: 2018-11-25；2019-02-15报道回顾 | C7: BitShares bitUSD：全局清算后借币停止 | D7: bitUSD；BTS为抵押资产 | E7: BitShares | F7: 加密资产超额抵押；BTS抵押支持bitUSD | G7: bitUSD是全局清算后停止新增借币并长期脱锚的稳定币 | H7: C_VS | I7: 核心机制 | J7: 核心机制—价值支撑风险 | K7: 稳定币特有风险 | L7: BTS持续下跌使抵押不足恶化，系统触发Global Settlement并停止常规新增借币 | M7: BTS抵押价值下降 → 系统抵押率恶化 → Global Settlement → 停止新增借币 → bitUSD长期脱锚 | N7: 是 | O7: 发生明显或持续性脱锚/折价，价格稳定性受到实质破坏；触发Global Settlement后长期停止新增借币并低于1美元 | P7: 触发Global Settlement后长期停止新增借币并低于1美元 | Q7: bitUSD进入全局清算并长期受限，后续社区通过机制提案讨论恢复和防止再次触发 | R7: C→M | T7: 事件依据 | U7: 资产证明
A8: 4 | B8: 2020-11—2023-04被指行为；2024-09-24公告 | C8: TrueCoin／TrustToken：TUSD储备披露与SEC和解 | D8: TUSD | E8: TUSD储备与离岸基金 | F8: 法币/RWA储备型TUSD；储备曾配置离岸投资基金 | G8: TUSD是储备披露与离岸基金投资安排的监管对象 | H8: C_VS | I8: 核心机制 | J8: 核心机制—价值支撑风险 | K8: 稳定币特有风险 | L8: TUSD储备资金被大量配置到离岸投资基金，实际资产安排与对外储备陈述之间出现重大差异 | M8: 储备投向离岸基金 → 资产透明度/合规性下降 → 监管调查 → SEC和解并要求整改 | N8: 否 | O8: TUSD未以事件期市场脱锚作为主要监管事实；核心是储备质量、流动性和披露真实性。 | P8: 超过5亿美元TUSD储备被投入离岸基金；SEC称到2024年约99%储备位于该基金 | Q8: TrueCoin/TrustToken与SEC达成和解并接受处罚/整改，TUSD储备透明度成为监管重点 | R8: C→E | T8: 事件依据 | U8: 资产证明
A9: 5 | B9: 2022-04—2022-12（多次脱锚） | C9: Neutrino Protocol | D9: USDN | E9: Waves | F9: 加密资产支持／算法型；WAVES-USDN铸赎与再资本化 | G9: USDN是直接脱锚对象，WAVES价值与资本化能力构成其核心支撑 | H9: C_VS | I9: 核心机制 | J9: 核心机制—价值支撑风险 | K9: 稳定币特有风险 | L9: WAVES价格下跌、抵押关联度高及再资本化能力不足，使USDN价值支撑持续承压 | M9: WAVES支撑能力下降 → USDN抵押不足/信心恶化 → 持续脱锚 → 再资本化与机制调整 → XTN转型 | N9: 是 | O9: 发生明显或持续性脱锚/折价，价格稳定性受到实质破坏；2022年4月USDN一度约0.78美元，年内反复脱锚，最终停止维持1美元目标并转为XTN | P9: 2022年4月USDN一度约0.78美元，年内反复脱锚，最终停止维持1美元目标并转为XTN | Q9: USDN经过多轮参数调整仍未恢复稳定，最终更名XTN并放弃固定1美元目标 | R9: C→M | T9: 事件依据 | U9: 资产证明
A10: 6 | B10: 2022-10-24 | C10: NEAR USN：停止铸造与受控退出 | D10: USN | E10: NEAR／Decentral Bank | F10: 混合机制USN；由算法模式转向更强抵押支持 | G10: USN是出现约4000万美元抵押缺口后停止铸造并受控退出的稳定币 | H10: C_VS | I10: 核心机制 | J10: 核心机制—价值支撑风险 | K10: 稳定币特有风险 | L10: 历史机制与资产负债表累积约4000万美元抵押缺口，继续铸造将扩大未覆盖负债 | M10: 发现约4000万美元抵押缺口 → 停止新铸USN → NEAR保护计划接管缺口 → 受控清算退出 | N10: 否 | O10: USN在发现约4,000万美元抵押缺口后停止新铸造并由NEAR保护计划承接，未以无序市场脱锚作为主要处置路径。 | P10: 约4,000万美元抵押缺口，由NEAR保护计划承担并推动退出 | Q10: Decentral Bank停止USN新铸造，NEAR保护计划承担缺口并推进持有人受控退出 | R10: C | T10: 事件依据 | U10: 资产证明
A11: 7 | B11: 2022-12—2023-02；后续机制说明至2023-07 | C11: USDN：年末失稳处置与XTN转型 | D11: Waves原生USDN，后更名XTN；ERC20映射另论 | E11: Waves主网 | F11: 加密资产支持／算法型；WAVES-USDN铸赎与再资本化 | G11: USDN是持续脱锚并最终转型为XTN的稳定币 | H11: C_VS | I11: 核心机制 | J11: 核心机制—价值支撑风险 | K11: 稳定币特有风险 | L11: WAVES/生态信用持续恶化与抵押结构弱化，使USDN多次脱锚后难以恢复 | M11: 支撑资产/生态信心走弱 → 多轮抛售与赎回 → USDN持续脱锚 → 机制调整与债务处置 → XTN转型 | N11: 是 | O11: 发生明显或持续性脱锚/折价，价格稳定性受到实质破坏；2022年4月最低约0.78美元，后续长期低于锚定并转型XTN | P11: 2022年4月最低约0.78美元，后续长期低于锚定并转型XTN | Q11: USDN最终转型XTN并放弃固定美元锚定，Waves生态转向新的风险处置机制 | R11: C→M | T11: 事件依据 | U11: 资产证明
A12: 8 | B12: 2023-03-10—2023-03-15 | C12: SVB 冲击 USDC | D12: USDC／USD Coin | E12: 储备银行／多链；研究覆盖Ethereum、Avalanche、Solana、TRON | F12: 法币储备型；USDC以现金及高流动性美元资产支持 | G12: USDC是链下储备银行风险直接传导至链上价格与赎回预期的稳定币 | H12: C_VS | I12: 核心机制 | J12: 核心机制—价值支撑风险 | K12: 稳定币特有风险 | L12: SVB关闭导致Circle有33亿美元储备暂时面临银行可用性风险，市场先行重估兑付预期 | M12: SVB关闭 → USDC部分储备短时不可用 → 赎回担忧与抛售 → USDC脱锚 → 政策保障/银行可用性恢复 → 回锚 | N12: 是 | O12: 发生明显或持续性脱锚/折价，价格稳定性受到实质破坏；Circle披露33亿美元USDC储备位于SVB；USDC一度跌至约0.87—0.88美元 | P12: Circle披露33亿美元USDC储备位于SVB；USDC一度跌至约0.87—0.88美元 | Q12: 美国监管处置SVB存款风险后Circle恢复赎回，USDC在数日内回到1美元附近 | R12: C→M | T12: 事件依据 | U12: 资产证明
A13: 9 | B13: 2023-10-11失稳；处置材料至2025-09-16 | C13: USDR：房地产储备与即时兑付缺口 | D13: Tangible Real USD（USDR）；非其他同符号代币 | E13: Polygon；2024赎回安排迁至re.al，2025拟返回Polygon | F13: RWA储备型；房地产+DAI等流动储备 | G13: USDR是房地产储备与有限流动储备共同支持、发生兑付危机的稳定币 | H13: C_VS | I13: 核心机制 | J13: 核心机制—价值支撑风险 | K13: 稳定币特有风险 | L13: 大部分储备为房地产等非即时流动资产，而可立即赎回的DAI储备规模有限 | M13: 市场赎回加速 → 约1180万DAI流动储备耗尽 → 房地产难即时变现 → 兑付预期崩塌 → USDR暴跌 | N13: 是 | O13: 发生明显或持续性脱锚/折价，价格稳定性受到实质破坏；约1,180万DAI流动储备被迅速耗尽，USDR价格大幅崩跌 | P13: 约1,180万DAI流动储备被迅速耗尽，USDR价格大幅崩跌 | Q13: Tangible停止正常USDR机制并推进赎回/资产处置，持有人通过后续安排回收价值 | R13: C→M | T13: 事件依据 | U13: 资产证明
A14: 10 | B14: 2025-04-16退出提案；2025-07-02完成 | C14: Inter Protocol／IST：分阶段停止运行 | D14: IST | E14: Agoric／Inter Protocol | F14: 多抵押+PSM稳定币IST；链上治理管理Vault与兑付模块 | G14: IST是治理决定分阶段停止Vault/PSM并退出的稳定币 | H14: C_VS | I14: 核心机制 | J14: 核心机制—价值支撑风险 | K14: 稳定币特有风险 | L14: 治理决定停止IST生态，Vault/PSM和债务头寸按计划分阶段关闭 | M14: 治理通过退出 → Vault/PSM停止扩张 → 用户偿还/赎回 → IST负债与供应逐步收缩 | N14: 否 | O14: IST按治理计划退出，没有以安全攻击或无序脱锚为主要结果；供应随债务关闭收缩。 | P14: 无攻击损失；IST的Vault/PSM和债务体系按治理计划退出 | Q14: Inter Protocol按治理方案完成/推进Vault、PSM与债务退出，IST供应逐步收缩 | R14: C | S14: 治理退出方向明确；具体全部完成节点以社区治理资料为主 | T14: 事件依据 | U14: 资产证明
A15: 11 | B15: 2025-05-12起；2025-08-22进入第三阶段 | C15: Mountain USDM：退出转向Uniswap与USDC储备 | D15: USDM（退出期转为USDC储备/AMM退出） | E15: Ethereum／Uniswap V4退出池 | F15: 收益型法币/RWA储备USDM；退出后转为USDC+AMM流动性 | G15: USDM是发行方主动退出并改变赎回/储备结构的稳定币 | H15: C_VS | I15: 核心机制 | J15: 核心机制—价值支撑风险 | K15: 稳定币特有风险 | L15: 发行人主动wind-down，直接美元赎回逐步转为USDC储备和Uniswap流动性退出 | M15: 主动停止发行 → 赎回模式切换 → USDC储备/Uniswap承接退出 → USDM供应逐步收缩 | N15: 否 | O15: USDM按wind-down计划退出，未以无序脱锚收尾；主要表现为供应收缩和赎回路径迁移。 | P15: 无攻击损失；USDM发行退出并将剩余退出流动性迁移至USDC/Uniswap | Q15: Mountain按wind-down计划停止常规发行，将退出路径转为USDC储备和Uniswap市场 | R15: C | T15: 事件依据 | U15: 资产证明
A16: 12 | B16: 2025-10-08公告；2025-12-08计划转换 | C16: Paxos USDL：停止发行与迁移USDG安排 | D16: USDL；迁移目标USDG | E16: Ethereum／Paxos发行体系 | F16: 法币/T-bill储备收益型USDL；发行人主导赎回与迁移 | G16: USDL是停止发行、收益和直接美元赎回并迁移至USDG的稳定币 | H16: C_VS | I16: 核心机制 | J16: 核心机制—价值支撑风险 | K16: 稳定币特有风险 | L16: Paxos决定停止USDL发行、收益与直接美元赎回，并安排符合条件余额迁移为USDG | M16: 停止USDL发行与收益 → 直接美元赎回终止 → 小额/合格余额转换USDG → 产品退出 | N16: 否 | O16: USDL有序退出，未以市场脱锚为主要事件结果；供应和收益功能按计划终止。 | P16: 无攻击损失；USDL停止铸造、收益和直接美元赎回并安排USDG转换 | Q16: Paxos按计划wind-down USDL并引导合格持有人迁移USDG，产品进入关闭阶段 | R16: C | T16: 事件依据 | U16: 资产证明
A17: 13 | B17: 2025-11-04（损失披露日） | C17: Stream xUSD：外部资产管理损失与退出暂停 | D17: Stream Finance xUSD | E17: 外部基金管理＋Euler／Morpho／Silo等DeFi依赖 | F17: 收益型合成美元；资产由外部基金经理及DeFi借贷策略管理 | G17: xUSD是外部资产管理亏损后暂停赎回并严重折价的稳定币 | H17: C_VS | I17: 核心机制 | J17: 核心机制—价值支撑风险 | K17: 稳定币特有风险 | L17: 外部基金管理人披露约9300万美元资产损失，Stream暂停存取款并暴露复杂DeFi敞口 | M17: 链下资产管理损失 → Stream暂停存取款 → xUSD兑付信心崩溃 → DeFi借贷敞口传染 → xUSD严重折价 | N17: 是 | O17: 发生明显或持续性脱锚/折价，价格稳定性受到实质破坏；Stream披露外部基金管理人损失约9,300万美元；xUSD最低约0.26美元，DeFi潜在敞口约2.85亿美元 | P17: Stream披露外部基金管理人损失约9,300万美元；xUSD最低约0.26美元，DeFi潜在敞口约2.85亿美元 | Q17: Stream暂停提款并进入调查/重组，xUSD严重失稳且外部DeFi协议被迫处置敞口 | R17: C→M→E→M | S17: Stream公开约9300万美元外部管理损失；具体损失形成时间和资产构成披露有限 | T17: 事件依据 | U17: 资产证明
A18: 14 | B18: 2026-05-15公告；初始赎回期至2026-11-11 | C18: GMO Trust：GYEN与ZUSD共同退出发行 | D18: GYEN、ZUSD | E18: Ethereum／GMO Trust发行体系 | F18: 法币储备型；GYEN锚定JPY、ZUSD锚定USD | G18: GYEN和ZUSD是发行人主动进入有序退出和赎回期的稳定币 | H18: C_VS | I18: 核心机制 | J18: 核心机制—价值支撑风险 | K18: 稳定币特有风险 | L18: GMO Trust主动停止GYEN/ZUSD新发行并设定统一赎回窗口 | M18: 停止GYEN/ZUSD新发行 → 进入赎回窗口 → 供应逐步收缩 → 产品有序退出 | N18: 否 | O18: GYEN/ZUSD有序退出，未以系统性脱锚为主要事件结果；核心是发行和赎回生命周期结束。 | P18: 无攻击损失；GYEN/ZUSD进入约180天初始赎回期 | Q18: GMO Trust停止GYEN/ZUSD新发行并维持赎回窗口，产品进入有序退出 | R18: C | T18: 事件依据 | U18: 资产证明
A19: 15 | B19: 2021-01-07 | C19: PolBase Cash特权提现／疑似Rug Pull | D19: PBC | E19: Ethereum | F19: 算法型；PBC/PBB/PBS三Token seigniorage结构 | G19: PBC是项目算法稳定币；资金损失来自管理员提取质押资产 | H19: C_PR | I19: 核心机制 | J19: 链上协议—协议规则缺陷 | K19: 继承风险 | L19: 部署者可通过setOperation等特权入口变更资金控制者并提取staking资产 | M19: 管理员设置资金操作地址 → staking资产被提取并撤流动性 → PBC生态信心与流动性受损 | N19: 否 | O19: 未观察到PBC系统性价格数据可可靠量化；主要表现为质押资产被特权地址提取和项目流动性损失。 | P19: 约353,807美元质押/流动性资产被提取 | Q19: 项目流动性/质押资产被提走后失去正常运营能力，按疑似Rug Pull记录 | R19: C→M | S19: 链上权限与资金转移可核，但缺少项目官方技术复盘 | T19: 事件依据 | U19: 资产证明
A20: 16 | B20: 2021-03-15 | C20: True Seigniorage Dollar | D20: TSD | E20: BSC | F20: 无抵押算法型；seigniorage与DAO治理 | G20: TSD是治理被接管后被巨量异常铸造的算法稳定币 | H20: C_PR | I20: 核心机制 | J20: 链上协议—协议规则缺陷 | K20: 继承风险 | L20: TSD价格低迷和治理参与下降使攻击者能低成本积累足够治理权并升级恶意实现 | M20: 治理参与枯竭 → 攻击者买入并控制提案 → 恶意升级 → 巨量TSD铸造 → 薄流动性市场被抽取 | N20: 是 | O20: 发生明显或持续性脱锚/折价，价格稳定性受到实质破坏；异常铸造约118亿TSD，但薄流动性下实际套现约1.66万美元 | P20: 异常铸造约118亿TSD，但薄流动性下实际套现约1.66万美元 | Q20: TSD供应和市场功能遭破坏，项目未形成有效恢复 | R20: C→M | S20: 治理攻击机制明确；约118亿TSD是异常铸造量，不等于同额美元损失 | T20: 事件依据 | U20: 资产证明
A21: 17 | B21: 2021-08-04（执行约01:43:52—01:49:05 UTC） | C21: Wault／WUSD：固定兑价与储备换币反馈 | D21: WUSD；USDT为主要储备，WEX为内生资产 | E21: BSC | F21: 混合储备；约90% USDT+10% WEX支持WUSD | G21: WUSD是固定USDT兑价和WEX储备反馈被反向利用的稳定币 | H21: C_PR | I21: 核心机制 | J21: 链上协议—协议规则缺陷 | K21: 重塑风险 | L21: WUSD按固定1:1 USDT铸赎，而相关操作同时影响WEX市场价格，形成可循环套利反馈 | M21: 固定USDT兑价铸赎 → WEX市场价格被操作影响储备 → 循环套利 → WUSD储备/锚定承压 | N21: 是 | O21: 发生明显或持续性脱锚/折价，价格稳定性受到实质破坏；约80万美元直接损失，WUSD稳定机制与储备承受冲击 | P21: 约80万美元直接损失，WUSD稳定机制与储备承受冲击 | Q21: Wault修复WUSD储备/兑换机制并处置损失，事件暴露固定兑价与内生Token反馈问题 | R21: C→M | T21: 事件依据 | U21: 资产证明
A22: 18 | B22: 2021-11-11 | C22: Mochi Finance | D22: USDM | E22: Ethereum | F22: 抵押借贷型；MOCHI等抵押生成USDM | G22: USDM是由项目方高权限抵押/发行安排扩张并进入外部池的稳定币 | H22: C_PR | I22: 核心机制 | J22: 链上协议—协议规则缺陷 | K22: 重塑风险 | L22: 项目方可大量铸MOCHI并影响其价格，同时以高LTV借出USDM，发行约束高度集中 | M22: 特权铸造MOCHI/控制估值 → 大量借出USDM → 换走DAI并购买CVX → Curve撤销激励 → USDM池失衡与折价 | N22: 是 | O22: 发生明显或持续性脱锚/折价，价格稳定性受到实质破坏；约4,600万USDM被生成/借出并换取DAI；相关Curve池流动性峰值曾超过1.7亿美元 | P22: 约4,600万USDM被生成/借出并换取DAI；相关Curve池流动性峰值曾超过1.7亿美元 | Q22: Curve Emergency DAO撤销USDM gauge激励，USDM市场流动性与可信度显著下降 | R22: C→M | S22: Curve治理记录与链上行为支持核心过程；更适合归为高度集中权限/经济治理风险 | T22: 事件依据 | U22: 资产证明
A23: 19 | B23: 2022-04-13 | C23: Elephant Money | D23: TRUNK | E23: BSC | F23: 储备／双Token机制；TRUNK与ELEPHANT生态联动 | G23: TRUNK是Reserve与ELEPHANT回购/铸赎反馈中的稳定资产 | H23: C_PR | I23: 核心机制 | J23: 链上协议—协议规则缺陷 | K23: 重塑风险 | L23: TRUNK mint/redeem、Reserve与ELEPHANT回购之间缺少严格资产会计不变量 | M23: 闪电贷改变ELEPHANT/TRUNK状态 → mint/redeem与回购反馈失真 → Reserve被抽取 → TRUNK支撑能力受损 | N23: 局部/短时 | O23: TRUNK相关市场在攻击后承压并出现短时价格扰动；核心损失是Reserve约1,120万美元被抽取，而非长期死亡螺旋。 | P23: 官方确认损失27,416 BNB，按当时价格约1,120万美元 | Q23: Elephant暂停Reserve与TRUNK铸赎并调整机制；协议储备受到实质损失 | R23: C→M | T23: 事件依据 | U23: 资产证明
A24: 20 | B24: 2022/4/17 | C24: Beanstalk 治理攻击 | D24: Bean／BEAN（事件时版本） | E24: Ethereum | F24: 信用／算法型；Beanstalk治理与内生信用机制 | G24: BEAN是协议负债与治理攻击后的价值受损对象 | H24: C_PR | I24: 核心机制 | J24: 链上协议—协议规则缺陷 | K24: 继承风险 | L24: 治理投票权可被闪电贷瞬时集中，攻击者利用紧急治理提案转移协议资产 | M24: 治理权瞬时集中 → 恶意提案通过 → 协议资产被转走 → BEAN信用受损与市场折价 | N24: 是 | O24: 发生明显或持续性脱锚/折价，价格稳定性受到实质破坏；约7,700万美元非BEAN资产被盗；协议估计总经济损失约1.82亿美元 | P24: 约7,700万美元非BEAN资产被盗；协议估计总经济损失约1.82亿美元 | Q24: Beanstalk通过融资/重启恢复协议运行，并重构治理安全机制 | R24: C→M | T24: 事件依据 | U24: 资产证明
A25: 21 | B25: 2023-09-21 | C25: Linear Finance发行权限失陷 | D25: lUSD（小写） | E25: BSC | F25: 合成资产债务池；ℓUSD由Linear合成资产体系支持 | G25: ℓUSD是攻击者用无限铸造的ℓAAVE在系统内兑换并对外抛售的稳定币 | H25: C_PR | I25: 核心机制 | J25: 链上协议—协议规则缺陷 | K25: 重塑风险 | L25: 高权限角色被异常授予ISSUE_ASSET权限，攻击合约获得合法无限发行ℓAAVE能力 | M25: ISSUE_ASSET权限失陷 → 无限铸ℓAAVE → 内部换成ℓUSD → 外部市场抛售 → ℓUSD流动性被抽干 | N25: 是 | O25: 发生明显或持续性脱锚/折价，价格稳定性受到实质破坏；约21.2万美元级攻击收益；ℓUSD主要流动性被快速抽干 | P25: 约21.2万美元级攻击收益；ℓUSD主要流动性被快速抽干 | Q25: Linear暂停mint/burn/exchange及桥接并追踪攻击地址，ℓUSD流动性随后重建有限 | R25: C→M | T25: 事件依据 | U25: 资产证明
A26: 22 | B26: 2026/3/22 | C26: Resolv／USR 异常铸造（扩充候选） | D26: USR（非USDe） | E26: Ethereum | F26: 市场中性储备型；USR依赖抵押资产与链下授权铸币 | G26: USR是发行权限失陷后被大量无储备异常铸造的稳定币 | H26: C_PR | I26: 核心机制 | J26: 链上协议—协议规则缺陷 | K26: 重塑风险 | L26: 链下授权/签名发行权限被攻陷，攻击者可绕过正常抵押/入金流程铸造USR | M26: 发行权限被攻陷 → USR无抵押巨量铸造 → 抛售/流动性抽取 → USR价格崩溃 → 项目应急处置 | N26: 是 | O26: 发生明显或持续性脱锚/折价，价格稳定性受到实质破坏；攻击者异常铸造约8,000万USR，USR随后跌至几美分水平 | P26: 攻击者异常铸造约8,000万USR，USR随后跌至几美分水平 | Q26: Resolv暂停/调整发行权限和相关合约，USR生态遭受严重信用与市场损失 | R26: C→M | S26: 安全机构与项目通报支持约8000万USR异常铸造；发行权限具体攻陷入口以公开资料为准 | T26: 事件依据 | U26: 资产证明
A27: 23 | B27: 2026-05-23—05-25；2026-08-25更新 | C27: StablR USDR／EURR未经授权发行 | D27: StablR USDR、EURR（区别Tangible USDR） | E27: StablR发行基础设施／链上USDR与EURR | F27: 法币储备型；USDR/EURR依赖发行基础设施与隔离储备 | G27: USDR/EURR是发行基础设施被攻陷后产生无对应储备供应的稳定币 | H27: C_PR | I27: 核心机制 | J27: 链上协议—协议规则缺陷 | K27: 重塑风险 | L27: 发行基础设施被攻击，攻击者绕过“入金—储备—授权铸币”流程直接生成USDR/EURR | M27: 发行系统入侵 → 无入金USDR/EURR被铸造 → 总供应超过合法储备 → 铸赎/交易暂停 → 调查与处置 | N27: 否 | O27: 未以市场脱锚作为核心结果；首要问题是链上未经授权供应超过合法储备覆盖范围，铸赎被暂停。 | P27: 未经授权供应约1,433万USDR和641万EURR，均无对应客户入金和新增储备 | Q27: StablR暂停USDR/EURR铸赎及交易协作，调查未经授权供应并保护合法储备 | R27: C | S27: StablR官方披露未经授权供应规模；具体密钥/多签攻陷路径未完全公开 | T27: 事件依据 | U27: 资产证明
A28: 24 | B28: 2020-11-17 | C28: Origin Protocol | D28: OUSD | E28: Ethereum | F28: 储备收益型；USDC/USDT/DAI等底层资产支持OUSD | G28: OUSD是铸币/重入会计漏洞直接异常生成的收益型稳定币 | H28: C_CI | I28: 核心机制 | J28: 链上协议—合约实现缺陷 | K28: 重塑风险 | L28: OUSD mint路径缺少完整资产校验和重入保护，外部Token回调可重复进入会计流程 | M28: 恶意Token回调重入 → OUSD铸币/rebase重复记账 → 异常OUSD赎回 → 储备被抽走 → OUSD折价 | N28: 是 | O28: 发生明显或持续性脱锚/折价，价格稳定性受到实质破坏；约700万—770万美元储备资产损失 | P28: 约700万—770万美元储备资产损失 | Q28: Origin暂停OUSD并补偿受影响用户，之后以更严格安全控制重启 | R28: C→M | T28: 事件依据 | U28: 资产证明
A29: 25 | B29: 2021-06-22—2021-06-29 | C29: Haven Protocol | D29: xUSD | E29: Haven | F29: 加密资产支持／隐私合成资产；XHV与xUSD/xAssets转换 | G29: xUSD是资产转换验证漏洞导致异常生成的核心稳定资产 | H29: C_CI | I29: 核心机制 | J29: 链上协议—合约实现缺陷 | K29: 重塑风险 | L29: mint/burn、价格记录与隐私资产转换验证存在多处边界条件和一致性漏洞 | M29: 转换验证漏洞 → xUSD/xBTC等异常生成 → 供应可信度受损 → 协议暂停 → 硬分叉回滚异常状态 | N29: 否 | O29: 未以持续脱锚作为主要结果；核心风险是xUSD/xAssets异常增发，协议最终通过硬分叉回滚主要异常状态。 | P29: 异常生成约900万xUSD及其他xAssets；协议通过硬分叉回滚主要异常状态 | Q29: Haven暂停转换并经社区硬分叉回滚，重写mint/burn验证后恢复网络 | R29: C | T29: 事件依据 | U29: 资产证明
A30: 26 | B30: 2021-06-28 | C30: SafeDollar | D30: SDO | E30: Polygon | F30: 算法型；SDO与奖励／通缩Token生态 | G30: SDO是奖励会计漏洞导致天量异常增发并抛售的稳定币 | H30: C_CI | I30: 核心机制 | J30: 链上协议—合约实现缺陷 | K30: 重塑风险 | L30: 奖励公式未正确处理带转账销毁的PLX，反复存取可把lpSupply分母压至极小 | M30: PLX转账销毁反复压低lpSupply → 单位奖励被极端放大 → SDO天量增发 → 抛售抽干USDC/USDT → 归零 | N30: 是 | O30: 发生明显或持续性脱锚/折价，价格稳定性受到实质破坏；约24.8万美元，包含约202,230 USDC与46,000 USDT | P30: 约24.8万美元，包含约202,230 USDC与46,000 USDT | Q30: SafeDollar暂停并尝试补偿/重构，但SDO价格归零后未恢复 | R30: C→M | T30: 事件依据 | U30: 资产证明
A31: 27 | B31: 2022/3/23 | C31: Cashio 伪造抵押物铸币 | D31: CASH | E31: Solana／Ethereum（报告资金去向） | F31: 加密资产抵押；Saber LP Token抵押铸造CASH | G31: CASH是被无有效抵押异常铸造并抛售的核心稳定币 | H31: C_CI | I31: 核心机制 | J31: 链上协议—合约实现缺陷 | K31: 重塑风险 | L31: 抵押账户身份验证不完整，攻击者可构造伪造抵押路径通过铸币校验 | M31: 抵押校验绕过 → CASH无抵押增发 → 兑换真实稳定币 → 流动性被抽干 → CASH接近归零 | N31: 是 | O31: 发生明显或持续性脱锚/折价，价格稳定性受到实质破坏；约5,200万美元资产损失，CASH价格几乎归零 | P31: 约5,200万美元资产损失，CASH价格几乎归零 | Q31: Cashio停止正常运行，CASH未恢复有效稳定币功能 | R31: C→M | T31: 事件依据 | U31: 资产证明
A32: 28 | B32: 2022-07-28 | C32: Nirvana Finance：ANA定价曲线操纵致NIRV失稳 | D32: NIRV | E32: Solana | F32: 储备型算法稳定币；NIRV依赖ANA与协议金库 | G32: NIRV是金库被抽空后失去支持并脱锚的稳定币 | H32: C_CI | I32: 核心机制 | J32: 链上协议—合约实现缺陷 | K32: 重塑风险 | L32: ANA大额买入未按价格曲线正确提高边际价格，攻击者可低价买入后高价卖回金库 | M32: ANA定价曲线被绕过 → 低价大额买入 → 新高价卖回协议 → 金库被抽干 → NIRV失去支持并脱锚 | N32: 是 | O32: 发生明显或持续性脱锚/折价，价格稳定性受到实质破坏；约350万—360万美元金库资产被抽取，NIRV失去有效支撑 | P32: 约350万—360万美元金库资产被抽取，NIRV失去有效支撑 | Q32: Nirvana金库被抽空后停止正常运营，NIRV未恢复稳定币功能 | R32: C→M | T32: 事件依据 | U32: 资产证明
A33: 29 | B33: 2022-08-14 | C33: Acala Network | D33: aUSD | E33: Polkadot | F33: 多抵押稳定币；Acala抵押资产支持aUSD | G33: aUSD是奖励配置错误导致异常增发的核心稳定币 | H33: C_CI | I33: 核心机制 | J33: 链上协议—合约实现缺陷 | K33: 重塑风险 | L33: 新iBTC/aUSD池奖励参数/遗留逻辑配置错误，使正常领取奖励路径异常生成aUSD | M33: 奖励参数错误 → LP操作异常铸aUSD → 供应暴增 → 市场恐慌脱锚 → 链上治理冻结并销毁异常供应 | N33: 是 | O33: 发生明显或持续性脱锚/折价，价格稳定性受到实质破坏；异常铸造约30.22亿aUSD；绝大多数被识别、冻结并通过治理销毁 | P33: 异常铸造约30.22亿aUSD；绝大多数被识别、冻结并通过治理销毁 | Q33: Acala通过治理冻结、追踪并销毁绝大多数异常aUSD，后续逐步恢复链上服务 | R33: C→M | T33: 事件依据 | U33: 资产证明
A34: 30 | B34: 2022-11-08 | C34: Abracadabra旧价借款／新价自清算 | D34: MIM | E34: Ethereum | F34: 加密资产超额抵押；Cauldron抵押借出MIM | G34: MIM是利用旧/新价格状态不一致完成借款与自清算套利的稳定币 | H34: C_CI | I34: 核心机制 | J34: 链上协议—合约实现缺陷 | K34: 重塑风险 | L34: 借款偿付检查可使用缓存旧价，而清算先刷新新价，导致同一交易采用两套估值 | M34: 旧价通过偿付检查 → 主动刷新新价 → 自己仓位变为可清算 → 自清算套利约11万MIM | N34: 局部/短时 | O34: 出现局部或短时价格偏离，未观察到同等程度的全市场持续失稳；攻击者获利约110,911 MIM | P34: 攻击者获利约110,911 MIM | Q34: Abracadabra确认旧Cauldron逻辑问题并隔离风险，攻击规模有限且MIM未持续失稳 | R34: C→M | T34: 事件依据 | U34: 资产证明
A35: 31 | B35: 2022-12-23—2022-12-24 | C35: Defrost Finance | D35: H2O | E35: Avalanche | F35: 加密资产抵押；Defrost Vault抵押生成H2O | G35: H2O是Defrost抵押借贷体系稳定币，受管理员权限事件波及 | H35: C_CI | I35: 核心机制 | J35: 链上协议—合约实现缺陷 | K35: 继承风险 | L35: V1管理员权限被使用以加入恶意抵押品/预言机；权限来源是否外部失窃存在归因争议 | M35: 管理员权限被使用 → 恶意抵押/预言机加入 → 资产被抽走 → H2O体系受损 → 返还资金与退款处置 | N35: 否 | O35: H2O未形成可与资金损失同规模对应的系统性脱锚证据；核心影响是Defrost资金被抽走与权限信任危机。 | P35: V1损失超过1,200万美元；V2另约17万美元，后续大部分V1资金返还 | Q35: Defrost宣布遭攻击并建立退款方案；大部分V1资金返还，但权限归因争议保留 | R35: C | S35: 资金流失和owner权限使用明确，但“外部私钥失窃还是内部Rug Pull”无最终公开定论 | T35: 事件依据 | U35: 资产证明
A36: 32 | B36: 2023-02-03—2023-02-04 | C36: SperaxUSD | D36: USDs | E36: Arbitrum | F36: 抵押／收益型rebase稳定币USDs | G36: USDs是rebase余额迁移错误导致异常余额产生的稳定币 | H36: C_CI | I36: 核心机制 | J36: 链上协议—合约实现缺陷 | K36: 重塑风险 | L36: rebase账户迁移在“先向未部署合约地址转币、后部署合约”边界场景错误解释credits | M36: 迁移credits误作余额 → 11枚USDs触发数十亿异常余额 → 分批卖出真实资产 → 协议暂停与修复 | N36: 局部/短时 | O36: 异常USDs被分批卖出造成短时市场压力，但实际变现约30.9万USDs，未形成与97.9亿账面异常余额同规模的持续脱锚。 | P36: 账面异常余额约97.9亿USDs；实际卖出约30.9万USDs | Q36: Sperax快速暂停合约、修复迁移逻辑并处理异常供应，USDs恢复运行 | R36: C→M | T36: 事件依据 | U36: 资产证明
A37: 33 | B37: 2023-02-16 | C37: Platypus Finance | D37: USP | E37: Avalanche | F37: 超额抵押稳定币；LP资产抵押借出USP | G37: USP是债务仍在但抵押可被抽离后形成不足额支持的稳定币 | H37: C_CI | I37: 核心机制 | J37: 链上协议—合约实现缺陷 | K37: 重塑风险 | L37: emergencyWithdraw在债务未清偿时允许抵押品被取回，提款后偿付能力未被正确验证 | M37: 紧急提款偿付检查缺口 → 借出USP后取回抵押 → 无抵押USP进入市场 → 真实稳定币被换走 → USP脱锚 | N37: 是 | O37: 发生明显或持续性脱锚/折价，价格稳定性受到实质破坏；三轮相关攻击合计约919万美元；首轮约850万美元 | P37: 三轮相关攻击合计约919万美元；首轮约850万美元 | Q37: Platypus暂停协议并开展资产回收、补偿和技术修复；USP未恢复原有规模 | R37: C→M | T37: 事件依据 | U37: 资产证明
A38: 34 | B38: 2023-02-21 | C38: Kujira USK Margin估值漏洞 | D38: USK | E38: Kujira | F38: 加密资产超额抵押；USK抵押债务体系 | G38: USK是Margin合约错误估值下被异常铸造并形成坏账的稳定币 | H38: C_CI | I38: 核心机制 | J38: 链上协议—合约实现缺陷 | K38: 重塑风险 | L38: USK Margin对买入资产价值/订单执行校验错误，可用新铸USK高价接攻击者自有ETH卖单 | M38: Margin错误估值 → 新铸USK高价买入攻击者ETH → USK坏账 → 团队用USDC托底稳定性 | N38: 否 | O38: USK整体锚定未出现持续性崩溃；团队以USDC补足约23.6万USK坏账以维持抵押状态。 | P38: 形成约23.6万USK坏账，约26万美元量级 | Q38: Kujira以USDC买入/补足风险资产并修复Margin，USK维持整体抵押状态 | R38: C | T38: 事件依据 | U38: 资产证明
A39: 35 | B39: 2023-05-06 | C39: DEUS Finance | D39: DEI | E39: BSC、Arbitrum | F39: 混合抵押稳定币；DEI依赖抵押与DeFi流动性 | G39: DEI是Token授权逻辑缺陷直接影响的稳定币资产 | H39: C_CI | I39: 核心机制 | J39: 链上协议—合约实现缺陷 | K39: 继承风险 | L39: DEI burnFrom读取allowance时颠倒owner/spender索引，破坏授权语义 | M39: allowance索引错误 → 授权关系被颠倒 → 用户DEI可被转走 → 多链损失与DEI大幅下跌 | N39: 是 | O39: 发生明显或持续性脱锚/折价，价格稳定性受到实质破坏；跨链损失约630万—650万美元 | P39: 跨链损失约630万—650万美元 | Q39: DEUS暂停DEI合约并协调白帽/攻击资金返还；项目后续逐步退出DEI | R39: C→M | T39: 事件依据 | U39: 资产证明
A40: 36 | B40: 2023-07-24 | C40: Palmswap | D40: USDP | E40: BSC | F40: DEX内部稳定资产；Vault资产支持USDP/PLP体系 | G40: USDP是Palmswap内部结算资产；核心漏洞发生在PLP/Vault份额定价 | H40: C_CI | I40: 核心机制 | J40: 链上协议—合约实现缺陷 | K40: 重塑风险 | L40: Vault资产余额可在不同比例铸造PLP的情况下被直接增加，导致PLP单位价值被人为抬高 | M40: Vault资产增加但PLP供应不增 → PLP单价虚高 → 高价赎回 → 约90万USDT被抽走 | N40: 否 | O40: 未观察到有证据支持的系统性脱锚；主要影响体现为供应、储备、资金损失、兑付或服务可用性变化。 | P40: 攻击者获利约901,455 USDT，后返还约80% | Q40: 攻击者返还约80%资金，Palmswap修复Vault/manager限制并恢复部分服务 | R40: C | T40: 事件依据 | U40: 资产证明
A41: 37 | B41: 2023-11-10 | C41: Raft Finance | D41: R | E41: Ethereum | F41: 加密资产超额抵押；LST抵押借出R | G41: R是虚假抵押份额支持下被异常借出的稳定币 | H41: C_CI | I41: 核心机制 | J41: 链上协议—合约实现缺陷 | K41: 重塑风险 | L41: 捐赠可操纵collateralIndex，极小额存款又因向上舍入产生不应存在的抵押份额 | M41: 捐赠抬高collateralIndex → 向上舍入制造虚假share → 抵押能力虚增 → R被异常借出 → R脱锚 | N41: 是 | O41: 发生明显或持续性脱锚/折价，价格稳定性受到实质破坏；约670万R被异常借出；攻击者后续误将约1,570 ETH发送至不可恢复地址 | P41: 约670万R被异常借出；攻击者后续误将约1,570 ETH发送至不可恢复地址 | Q41: Raft暂停R铸造并制定恢复/赎回方案，R未恢复原有稳定币生态规模 | R41: C→M | T41: 事件依据 | U41: 资产证明
A42: 38 | B42: 2024-01-30 | C42: Abracadabra Money | D42: MIM | E42: Ethereum | F42: 加密资产超额抵押；Cauldron抵押借出MIM | G42: MIM是债务份额会计错误导致无充分抵押借出的稳定币 | H42: C_CI | I42: 核心机制 | J42: 链上协议—合约实现缺陷 | K42: 重塑风险 | L42: 债务elastic/base在特定还款路径后失配，舍入误差可被重复放大 | M42: 债务base/elastic失配 → 舍入偏差反复放大 → 债务被低估 → 约650万MIM异常借出 → MIM短时脱锚 | N42: 是 | O42: 发生明显或持续性脱锚/折价，价格稳定性受到实质破坏；约649万—650万美元MIM被异常借出 | P42: 约649万—650万美元MIM被异常借出 | Q42: Abracadabra隔离受影响Cauldron、修复债务会计并推进资金追踪；MIM随后回锚 | R42: C→M | T42: 事件依据 | U42: 资产证明
A43: 39 | B43: 2024-03-28 | C43: Prisma Finance | D43: mkUSD | E43: Ethereum | F43: 加密资产超额抵押；LST/LRT抵押借出mkUSD | G43: mkUSD是Prisma仓位债务稳定币，攻击重点在用户抵押仓位权限 | H43: C_CI | I43: 核心机制 | J43: 链上协议—合约实现缺陷 | K43: 继承风险 | L43: 迁移辅助合约flash-loan回调缺少对合法迁移调用链和参数的充分校验 | M43: 迁移回调校验不足 → 借用用户delegate权限关闭仓位 → 抵押物被抽走 → Prisma损失与仓位风险 | N43: 否 | O43: mkUSD未出现由该漏洞引发的系统性锚定崩溃；主要影响是Prisma用户抵押物被盗和协议暂停。 | P43: 约1,200万美元wstETH等抵押资产被转走 | Q43: Prisma暂停协议、修复迁移路径并与攻击者/执法推进资金追索 | R43: C | T43: 事件依据 | U43: 资产证明
A44: 40 | B44: 2024-07-30 | C44: Anzen Finance Blast Vault错误 | D44: USDz（Anzen；Blast Vault） | E44: Blast | F44: RWA/私人信贷支持的美元稳定币USDz | G44: USDz是Blast Vault漏洞中被白帽取得的稳定币 | H44: C_CI | I44: 核心机制 | J44: 链上协议—合约实现缺陷 | K44: 继承风险 | L44: Blast Vault的数值/decimal处理存在错误，使白帽可取得约50万USDz | M44: Blast Vault数值处理错误 → 白帽取得USDz → 项目回购/协商返还 → 绝大部分资金回收 | N44: 否 | O44: USDz未出现持续脱锚；白帽事件主要造成短时安全处置和回购压力。 | P44: 白帽取得约50万USDz；约45万美元等值资产返还，约5万美元作为赏金 | Q44: 白帽返还约90%资产，Anzen支付赏金并修复Blast Vault，USDz未出现持续失稳 | R44: C | S44: Blast Vault、50万USDz与返还事实可核；公开技术细节不足以进一步确定完整漏洞路径 | T44: 事件依据 | U44: 资产证明
A45: 41 | B45: 2025-03-01 | C45: Zoth／ZeUSD：抵押计量错误铸币 | D45: ZeUSD；USDC为入金，wM为换入抵押品 | E45: Ethereum／Zoth | F45: RWA/抵押型；USDC换入抵押资产后铸造ZeUSD | G45: ZeUSD是抵押计量错误下被超额铸造的稳定币 | H45: C_CI | I45: 核心机制 | J45: 链上协议—合约实现缺陷 | K45: 重塑风险 | L45: 抵押品计量/单位换算错误，使少量USDC换入资产后被记成远高于真实价值的ZeUSD抵押 | M45: 抵押单位计量错误 → 抵押价值虚高 → ZeUSD超额铸造 → 换出真实资产 → 协议损失 | N45: 否 | O45: 未观察到有证据支持的系统性脱锚；主要影响体现为供应、储备、资金损失、兑付或服务可用性变化。 | P45: 攻击者获利约28.5万美元 | Q45: Zoth暂停受影响铸币/抵押路径并修复计量逻辑，ZeUSD事件损失被隔离 | R45: C | T45: 事件依据 | U45: 资产证明
A46: 42 | B46: 2025-09-16（植入）—2025-12-04（利用） | C46: USPD：部署初始化劫持与延迟利用 | D46: USPD（可升级代理发行） | E46: Ethereum可升级代理体系 | F46: 可升级代理发行的美元稳定币；铸币权由代理权限控制 | G46: USPD是部署代理被植入恶意中间层后被异常铸造的稳定币 | H46: C_CI | I46: 核心机制 | J46: 链上协议—合约实现缺陷 | K46: 继承风险 | L46: 部署与initialize未原子完成，攻击者抢先初始化并在代理与合法实现之间植入恶意CPIMP | M46: 部署初始化被抢先 → CPIMP长期潜伏 → 攻击者启用隐藏控制权 → 异常铸USPD/转移stETH → 协议处置 | N46: 否 | O46: 未观察到有证据支持的系统性脱锚；主要影响体现为供应、储备、资金损失、兑付或服务可用性变化。 | P46: 异常铸造约9,800万USPD并转移约232 stETH；公开安全数据库记录实际损失约100万美元级 | Q46: USPD公开CPIMP复盘并修复代理/部署流程，异常供应与损失进入处置 | R46: C | S46: USPD官方CPIMP post-mortem提供部署、潜伏和利用链路 | T46: 事件依据 | U46: 资产证明
A47: 43 | B47: 2025-10-04 12:54:23 UTC | C47: Abracadabra：旧Cauldron V4偿付检查绕过 | D47: MIM | E47: Ethereum／Abracadabra旧Cauldron V4 | F47: 加密资产超额抵押；Cauldron抵押借出MIM | G47: MIM是旧Cauldron偿付检查被绕过后异常借出的稳定币 | H47: C_CI | I47: 核心机制 | J47: 链上协议—合约实现缺陷 | K47: 重塑风险 | L47: 旧Cauldron V4偿付检查存在状态/逻辑缺口，可在抵押不足时仍通过借款条件 | M47: 偿付检查绕过 → 抵押不足仍可借MIM → 约179万MIM被提取 → 旧市场被隔离/修复 | N47: 否 | O47: 未观察到有证据支持的系统性脱锚；主要影响体现为供应、储备、资金损失、兑付或服务可用性变化。 | P47: 约179万MIM被异常借出/提取 | Q47: Abracadabra暂停旧Cauldron V4相关市场并修复偿付检查，损失约179万MIM | R47: C | T47: 事件依据 | U47: 资产证明
A48: 44 | B48: 2022-03-15 | C48: DEUS Finance | D48: DEI | E48: Fantom | F48: 混合抵押稳定币；DEI依赖抵押与DeFi流动性 | G48: DEI价格被操纵后触发异常清算，是借贷体系的稳定资产 | H48: C_RD | I48: 核心机制 | J48: 链上协议—运行依赖风险 | K48: 重塑风险 | L48: 借贷系统采用可被闪电贷推动的DEI现货价格，正常仓位可被错误判定为可清算 | M48: DEI现货价被闪电贷压低/扰动 → 正常仓位被判清算 → 攻击者获利 → 协议形成损失 | N48: 局部/短时 | O48: 出现局部或短时价格偏离，未观察到同等程度的全市场持续失稳；攻击者获利约300万美元 | P48: 攻击者获利约300万美元 | Q48: DEUS修补价格预言机，但一个多月后再次发生不同预言机攻击 | R48: C→M | T48: 事件依据 | U48: 资产证明
A49: 45 | B49: 2022-04-28 | C49: DEUS Finance | D49: DEI | E49: Fantom | F49: 混合抵押稳定币；DEI依赖抵押与DeFi流动性 | G49: DEI是被操纵估值并用于异常借贷的稳定币 | H49: C_RD | I49: 核心机制 | J49: 链上协议—运行依赖风险 | K49: 重塑风险 | L49: DEI定价依赖可操纵的流动性市场/VWAP输入，异常交易可进入价格计算 | M49: DEI市场/VWAP被操纵 → 抵押价值虚高 → 过量借出资产 → 协议损失与DEI短时偏离 | N49: 局部/短时 | O49: 出现局部或短时价格偏离，未观察到同等程度的全市场持续失稳；攻击者收益约1,340万美元；安全机构估算协议影响约1,570万美元 | P49: 攻击者收益约1,340万美元；安全机构估算协议影响约1,570万美元 | Q49: DEUS暂停受影响借贷与价格路径并调整预言机；DEI恢复后仍经历后续安全事件 | R49: C→M | T49: 事件依据 | U49: 资产证明
A50: 46 | B50: 2022-05-21 | C50: bDollar | D50: BDO | E50: BSC | F50: 无抵押算法型；BDO seigniorage生态 | G50: BDO是被操纵价格并触发协议自动回购机制的算法稳定币 | H50: C_RD | I50: 核心机制 | J50: 链上协议—运行依赖风险 | K50: 重塑风险 | L50: Community Fund自动回购机制缺少对BDO异常价格、滑点和池深的充分约束 | M50: 先推高BDO → 触发Community Fund自动买入 → 协议成为高价接盘方 → 攻击者卖出BDO获利 | N50: 局部/短时 | O50: BDO价格在攻击过程中被人为推高并随后回落，属于短时操纵而非自然长期脱锚；攻击者获利约70万—80万美元。 | P50: 攻击者获得约2,381 BNB，约70万—80万美元 | Q50: bDollar相关生态受到流动性与价格冲击，自动回购机制暴露后被调整 | R50: C→M | T50: 事件依据 | U50: 资产证明
A51: 47 | B51: 2023-02-01 | C51: BonqDAO（Bonq 协议） | D51: BEUR | E51: Polygon | F51: 加密资产超额抵押；WALBT等抵押铸借BEUR | G51: BEUR是由被操纵抵押价值支持的借出稳定币 | H51: C_RD | I51: 核心机制 | J51: 链上协议—运行依赖风险 | K51: 重塑风险 | L51: Bonq对WALBT价格源的抗操纵约束不足，抵押估值可被短时大幅抬高/压低 | M51: WALBT价格操纵 → 抵押价值虚高/虚低 → 超额借BEUR并清算他人 → 坏账与BEUR压力 | N51: 局部/短时 | O51: 出现局部或短时价格偏离，未观察到同等程度的全市场持续失稳；协议层名义影响约1.2亿美元；大量BEUR/WALBT缺乏足够流动性，攻击者实际可兑现收益显著更低 | P51: 协议层名义影响约1.2亿美元；大量BEUR/WALBT缺乏足够流动性，攻击者实际可兑现收益显著更低 | Q51: Bonq暂停受影响市场并处置坏账；BEUR生态流动性和信用受到长期冲击 | R51: C→M | S51: Immunefi/Omniscia等技术复盘一致；名义损失与实际可兑现收益需区分 | T51: 事件依据 | U51: 资产证明
A52: 48 | B52: 2023-08-13 | C52: Zunami Protocol | D52: UZD | E52: Ethereum | F52: 收益型储备稳定币；策略资产支持UZD | G52: UZD的内部资产价值因策略储备估值被操纵而虚高 | H52: C_RD | I52: 核心机制 | J52: 链上协议—运行依赖风险 | K52: 重塑风险 | L52: 策略总资产估值依赖可操纵的SDT现货价格，且外部捐赠可同步放大资产数量 | M52: 捐赠SDT+操纵SDT价格 → 策略总资产虚增 → UZD内部价值被抬高 → 按虚高价值赎回真实资产 | N52: 是 | O52: 发生明显或持续性脱锚/折价，价格稳定性受到实质破坏；约210万—220万美元资产损失 | P52: 约210万—220万美元资产损失 | Q52: Zunami暂停相关稳定币/策略并推进补偿与重构，UZD市场规模显著收缩 | R52: C→M | T52: 事件依据 | U52: 资产证明
A53: 49 | B53: 2023-11-07 | C53: TheStandard／EUROs抵押交换漏洞 | D53: EUROs（被超额铸造）；PAXG为被利用抵押资产 | E53: Arbitrum | F53: 加密资产超额抵押；Smart Vault抵押铸造EUROs | G53: EUROs是以被异常置换/低估后的抵押仓位支持而超额借出的稳定币 | H53: C_RD | I53: 核心机制 | J53: 链上协议—运行依赖风险 | K53: 重塑风险 | L53: 抵押swap缺少充分滑点和独立价值校验，攻击者可自建低流动性PAXG市场制造劣价兑换 | M53: 自建PAXG薄池 → Vault按劣价交换高价值抵押 → 仓位抵押价值骤降 → EUROs形成不足额支持 | N53: 否 | O53: EUROs未出现长期系统性脱锚；核心影响是攻击仓位形成不足额抵押和约29万美元损失。 | P53: 约29万美元级损失/不足额抵押，主要资金后续得到返还 | Q53: TheStandard移除/限制相关collateral swap能力，主要资金后续返还 | R53: C | S53: Dedaub与项目资料支持；稳定币为EUROs，PAXG是被利用的抵押资产 | T53: 事件依据 | U53: 资产证明
A54: 50 | B54: 2025-06-26；技术报告2025-07-14 | C54: Resupply reUSD：空金库取价与超额借出 | D54: reUSD、crvUSD；wstUSR市场抵押份额 | E54: Ethereum | F54: 抵押借贷稳定币；依赖crvUSD市场与wstUSR抵押份额 | G54: reUSD是抵押市场估值被操纵后被超额借出的稳定币 | H54: C_RD | I54: 核心机制 | J54: 链上协议—运行依赖风险 | K54: 重塑风险 | L54: 空/低流动性金库价格可被少量操作极端扭曲，wstUSR抵押份额因此被严重高估 | M54: 低流动性价格被极端扭曲 → wstUSR抵押份额虚高 → 大量reUSD借出 → 坏账/损失约千万美元 | N54: 否 | O54: reUSD未以持续脱锚作为事件核心；主要后果是抵押估值错误造成约950万—1,000万美元坏账。 | P54: 协议损失约950万—1,000万美元 | Q54: Resupply暂停受影响市场并推进赔付/重构，损失形成协议坏账 | R54: C | T54: 事件依据 | U54: 资产证明
A55: 51 | B55: 2026-04-16 | C55: Money on Chain：预言机漏洞触发DOC铸赎暂停 | D55: DOC | E55: Rootstock／Money on Chain | F55: BTC超额抵押稳定币DOC；铸赎依赖BTC/USD预言机 | G55: DOC因OMoC预言机基础设施严重漏洞被主动暂停铸赎；漏洞未被利用 | H55: C_RD | I55: 核心机制 | J55: 链上协议—运行依赖风险 | K55: 重塑风险 | L55: 发现OMoC预言机基础设施严重漏洞，继续铸赎可能使DOC抵押与定价计算面临安全风险 | M55: 发现OMoC预言机漏洞 → 主动启动panic button暂停DOC铸赎 → 修复与验证 → 恢复服务 | N55: 否 | O55: DOC未发生已确认脱锚；协议主动停铸停赎以避免预言机漏洞被利用并演化为错误兑付。 | P55: 无已确认资金损失；漏洞未被利用，未发生错误报价 | Q55: Money on Chain主动启动panic button暂停DOC铸赎，完成修复与验证后恢复服务 | R55: C | S55: 官方复盘明确为OMoC预言机基础设施严重漏洞；漏洞未被利用，未发生错误报价或用户资金损失 | T55: 事件依据 | U55: 资产证明
A56: 52 | B56: 2018年3月持续讨论 | C56: NuBits：2018年锚定与分层流动性压力 | D56: NuBits／NBT；NuShares为支持资产 | E56: 多交易市场／NuBits | F56: 无抵押算法型；NuShares+流动性提供者维持NBT锚定 | G56: NuBits/NBT是流动性支持枯竭后长期偏离1美元的算法稳定币 | H56: M_LI | I56: 市场运行 | J56: 市场运行—流动性风险 | K56: 稳定币特有风险 | L56: 锚定主要依赖有限流动性提供者和NuShares融资支持；市场深度与支持资金持续不足 | M56: 流动性支持资金枯竭 → 买盘不足 → NBT跌破1美元 → 市场深度进一步下降 → 长期脱锚 | N56: 是 | O56: 发生明显或持续性脱锚/折价，价格稳定性受到实质破坏；2018年长期脱锚，NBT在多个阶段显著低于1美元 | P56: 2018年长期脱锚，NBT在多个阶段显著低于1美元 | Q56: NuBits未能恢复长期稳定锚定，项目流动性和市场影响力持续萎缩 | R56: M | S56: 长期脱锚事实充分；早期NuBits机制和流动性数据主要依赖项目社区历史资料 | T56: 事件依据 | U56: 资产证明
A57: 53 | B57: 2022-05-07—2022-05-13 | C57: Terra／UST 脱锚 | D57: UST（原生 Terra；本文交易为 Ethereum Wormhole UST） | E57: Terra／Ethereum | F57: 算法型；UST-LUNA内生铸赎 | G57: UST是直接失稳对象；LUNA承担内生赎回与吸收退出压力的机制角色 | H57: M_LI | I57: 市场运行 | J57: 市场运行—流动性风险 | K57: 重塑风险 | L57: 大额UST退出与Curve流动性失衡首先削弱锚定，市场套利随后通过LUNA铸赎吸收压力 | M57: 流动性集中退出 → UST跌破锚定 → LUNA赎回增发 → LUNA下跌 → 更大规模赎回与死亡螺旋 | N57: 是 | O57: 发生明显或持续性脱锚/折价，价格稳定性受到实质破坏；UST接近归零、LUNA价格崩溃；生态市值损失达到数百亿美元量级 | P57: UST接近归零、LUNA价格崩溃；生态市值损失达到数百亿美元量级 | Q57: Terra Classic生态进入崩溃与重组；UST更名USTC后长期未恢复1美元锚定 | R57: M→C→M | T57: 事件依据 | U57: 资产证明
A58: 54 | B58: 2025/4/2 | C58: FDUSD：储备争议与场所价格偏离 | D58: First Digital FDUSD；关联争议涉及TUSD托管方 | E58: Binance现货；发行和储备主体 | F58: 法币储备型稳定币或其外部使用/处置场景 | G58: FDUSD是受托管机构声誉冲击而短时折价的稳定币 | H58: M_LI | I58: 市场运行 | J58: 市场运行—流动性风险 | K58: 重塑风险 | L58: 针对First Digital Trust偿付能力的公开质疑引发持有人抢跑卖出，先于事实核验形成价格冲击 | M58: 托管方偿付质疑 → FDUSD集中卖出 → 局部市场折价约0.87 → 储备鉴证与赎回验证 → 快速回锚 | N58: 局部/短时 | O58: 出现局部或短时价格偏离，未观察到同等程度的全市场持续失稳；FDUSD最低约0.87美元，数小时内恢复至接近1美元 | P58: FDUSD最低约0.87美元，数小时内恢复至接近1美元 | Q58: First Digital否认资不抵债并继续处理赎回，FDUSD在数小时内恢复接近1美元 | R58: M | S58: 价格、鉴证与公开争议均可核；“托管方资不抵债”是指控而非既成事实 | T58: 事件依据 | U58: 资产证明
A59: 55 | B59: 2025-10-10—2025-10-11 | C59: USDe 场所价格偏离 | D59: USDe（非 sUSDe）；Binance USDEUSDT | E59: 中心化场所；对照链上市场 | F59: 合成美元；现货/衍生品delta-neutral对冲支持USDe | G59: USDe是特定交易场所短时价格偏离对象，核心储备/对冲未同步失效 | H59: M_LI | I59: 市场运行 | J59: 市场运行—流动性风险 | K59: 继承风险 | L59: 极端去杠杆下Binance订单簿买盘不足、清算集中，场所价格与链上/其他市场短时脱节 | M59: 极端行情去杠杆 → Binance清算与卖单集中 → 订单簿流动性不足 → 局部价格跌至约0.65 → 套利后修复 | N59: 局部/短时 | O59: 出现局部或短时价格偏离，未观察到同等程度的全市场持续失稳；Binance最低约0.65美元、低于0.90美元约23分钟；其他主要市场同期明显更接近1美元 | P59: Binance最低约0.65美元、低于0.90美元约23分钟；其他主要市场同期明显更接近1美元 | Q59: 极端行情结束与套利恢复后USDe快速回到正常区间，事件未演化为全市场偿付危机 | R59: M | T59: 事件依据 | U59: 资产证明
A60: 56 | B60: 2025-11-06 | C60: Stables Labs USDX：失稳与借贷市场处置 | D60: Stables Labs USDX／sUSDX | E60: Lista／PancakeSwap及相关借贷市场 | F60: 合成美元；抵押资产与delta-neutral对冲策略 | G60: USDX是失稳对象，并在多个借贷市场中作为抵押/债务资产放大风险 | H60: M_LI | I60: 市场运行 | J60: 市场运行—流动性风险 | K60: 重塑风险 | L60: USDX市场流动性与借贷抵押结构同时恶化；公开资料尚不能唯一确定最早技术触发点 | M60: 流动性恶化/高杠杆借贷压力 → USDX跌破1美元 → 抵押品价值下降 → 强制清算与二次卖压 → 深度脱锚 | N60: 是 | O60: 发生明显或持续性脱锚/折价，价格稳定性受到实质破坏；USDX从1美元快速跌破0.60美元并进一步失稳，相关借贷市场启动强制清算 | P60: USDX从1美元快速跌破0.60美元并进一步失稳，相关借贷市场启动强制清算 | Q60: 相关借贷协议执行强制清算和风险隔离；USDX信用与市场流动性受到持续冲击 | R60: M→E→M | S60: USDX严重脱锚和强制清算可核，但公开证据不足以唯一确定最早的单一技术触发点 | T60: 事件依据 | U60: 资产证明
A61: 57 | B61: 2020-12—2021-02（主要失稳窗口） | C61: ESD：2020年末至2021年初收缩困境 | D61: Empty Set Dollar V1（ESD）；不是DSD | E61: Ethereum主网；ESD/USDC Uniswap V2 | F61: 无抵押算法型；rebase/coupon供给调节 | G61: ESD是依赖coupon等市场参与机制恢复锚定的算法稳定币 | H61: M_PR | I61: 市场运行 | J61: 市场运行—锚定修复风险 | K61: 稳定币特有风险 | L61: 价格低于1美元后依赖用户主动销毁ESD换取未来coupon，收缩激励不足以吸引参与者 | M61: ESD跌破1美元 → coupon收缩机制需要用户主动烧币 → 参与不足 → 供应无法及时收缩 → 长期脱锚 | N61: 是 | O61: 发生明显或持续性脱锚/折价，价格稳定性受到实质破坏；ESD供应曾达到约5.5亿美元量级，随后长期跌破1美元并失去流动性 | P61: ESD供应曾达到约5.5亿美元量级，随后长期跌破1美元并失去流动性 | Q61: ESD长期低于1美元并失去主要流动性，算法稳定机制事实上退出主流使用 | R61: M→C→M | T61: 事件依据 | U61: 资产证明
A62: 58 | B62: 2021-04-03启动；2021-04-06—04-08首轮压力期 | C62: FEI：2021年4月启动与退出受限 | D62: FEI V1／ETH PCV | E62: Ethereum主网；Uniswap激励池与其他场所 | F62: 协议控制价值PCV；ETH资产+Direct Incentives稳定机制 | G62: FEI是Direct Incentives和PCV机制承压下折价的稳定币 | H62: M_PR | I62: 市场运行 | J62: 市场运行—锚定修复风险 | K62: 稳定币特有风险 | L62: Direct Incentives在压力期提高卖出成本，PCV不可按传统1:1储备方式直接赎回 | M62: FEI折价 → Direct Incentives提高卖出惩罚 → 退出摩擦上升 → 套利/需求不足 → 回锚缓慢 | N62: 是 | O62: 发生明显或持续性脱锚/折价，价格稳定性受到实质破坏；FEI上线后持续折价；同期另有Direct Incentives漏洞并支付30万美元赏金 | P62: FEI上线后持续折价；同期另有Direct Incentives漏洞并支付30万美元赏金 | Q62: Fei通过机制调整、激励和后续协议升级改善锚定，V1设计被逐步替代 | R62: M→C→M | T62: 事件依据 | U62: 资产证明
A63: 59 | B63: 2025-05-30（项目回锚说明） | C63: Synthetix sUSD：债务管理调整后的回锚 | D63: sUSD | E63: Synthetix债务池与公开市场 | F63: 合成资产债务池；sUSD由Synthetix债务体系支持 | G63: sUSD是债务激励变化后缺乏足够买盘修复锚定的稳定币 | H63: M_PR | I63: 市场运行 | J63: 市场运行—锚定修复风险 | K63: 稳定币特有风险 | L63: 债务制度调整削弱了持有人主动买入/承担sUSD债务的激励，二级市场修复力量不足 | M63: 债务激励调整 → 买入sUSD承担债务的经济动力下降 → 折价扩大 → 财政回购/参数调整 → 部分回锚 | N63: 是 | O63: 发生明显或持续性脱锚/折价，价格稳定性受到实质破坏；sUSD一度约0.70美元；Synthetix使用约200万美元财政资金等措施推动回锚 | P63: sUSD一度约0.70美元；Synthetix使用约200万美元财政资金等措施推动回锚 | Q63: Synthetix通过财政回购、债务激励与参数调整推动sUSD回锚，但持续监控仍必要 | R63: M | T63: 事件依据 | U63: 资产证明
A64: 60 | B64: 2021-06-16—2021-06-17 | C64: IRON／TITAN：Polygon 2021年6月失稳 | D64: IRON V1／TITAN；不是BSC IRON／STEEL | E64: Polygon主网 | F64: 部分抵押；约75% USDC+25% TITAN | G64: IRON是发生挤兑与脱锚的部分抵押稳定币，TITAN承担内生吸收机制 | H64: M_CR | I64: 市场运行 | J64: 市场运行—信心挤兑风险 | K64: 重塑风险 | L64: TITAN价格下跌触发IRON赎回，赎回又增发/抛售TITAN并进一步削弱市场信心 | M64: TITAN下跌 → IRON赎回增加 → 更多TITAN被铸出并抛售 → TITAN归零 → IRON进一步挤兑脱锚 | N64: 是 | O64: 发生明显或持续性脱锚/折价，价格稳定性受到实质破坏；TITAN从约60美元跌近0；IRON一度跌至0.75美元以下 | P64: TITAN从约60美元跌近0；IRON一度跌至0.75美元以下 | Q64: Polygon版IRON/TITAN体系崩溃，TITAN几乎归零，IRON未恢复原有稳定机制 | R64: M→C→M | T64: 事件依据 | U64: 资产证明
A65: 61 | B65: 2026-02-23 | C65: WLFI/USD1：负面信息冲击与短时价格偏离 | D65: World Liberty Financial USD1 | E65: 社交信息与聚合报价；Binance USD1/USDT现货 | F65: 法币储备型稳定币或其外部使用/处置场景 | G65: USD1为负面信息及项目信任扰动中出现短时市场价格偏离的稳定币；集中赎回未证实。 | H65: M_CR | I65: 市场运行 | J65: 市场运行—信心挤兑风险 | K65: 继承风险 | L65: WLFI相关负面信息与项目信任担忧出现，伴随USD1短时卖压；未证实更早的价值支撑、协议或外部服务实质性异常。 | M65: 负面信息与信任担忧 → USD1短时卖压及价格偏离 → 报价恢复接近平价 | N65: 局部/短时 | O65: 新闻转引的聚合报价最低约0.994美元；Binance USD1/USDT小时K线最低0.9802 USDT/USD1（2026-02-23 13:00–13:59 UTC），该小时收盘0.9974，15:00小时收盘0.9990。 | P65: 聚合报价约0.994美元与Binance现货最低0.9802 USDT/USD1属于不同观测口径；实际兑付损失和集中赎回规模未取得。 | Q65: WLFI否认智能合约或钱包受损，并称USD1储备充足；市场报价随后恢复接近平价。协调攻击归因来自项目方主张。 | R65: M | S65: 原始现货行情确认短时价格偏离；账号入侵、付费传播和WLFI代币做空为项目方主张，未取得独立技术调查证据；集中赎回与兑付损失未证实。 | T65: 事件依据 | U65: 资产证明
A66: 62 | B66: 2017-11-19 | C66: Tether | D66: USDT | E66: Omni Layer、Ethereum | F66: 法币储备型；USDT由发行人储备与赎回承诺支撑 | G66: USDT是发行方Treasury被盗资产，稳定机制本身未被攻破 | H66: E_IN | I66: 外部生态 | J66: 外部生态—外部集成风险 | K66: 继承风险 | L66: Tether Treasury/后台钱包基础设施被未授权访问并转出USDT | M66: Treasury被未授权转账 → 约3095万USDT进入攻击地址 → 发行方拒绝赎回/冻结 → 生态阻断流通 | N66: 否 | O66: USDT未出现系统性脱锚；发行方通过拒绝赎回和黑名单处置被盗Token，市场影响主要是可用性与中心化控制讨论。 | P66: 30,950,010 USDT从Tether Treasury被未授权转出 | Q66: Tether暂停相关钱包服务、标记被盗Token并通过Omni黑名单/客户端更新阻断流通 | R66: E | S66: Tether官方确认3095万USDT被盗；具体入侵技术路径未完整公开 | T66: 事件依据 | U66: 资产证明
A67: 63 | B67: 2021-03-16 | C67: Iron Finance vFarm奖励配置错误 | D67: IRON相关vFarm；异常发放资产为SIL | E67: BSC | F67: 部分抵押IRON生态；本事件发生于外部vFarm奖励模块 | G67: IRON仅作为受影响生态稳定币；直接异常资产是vFarm奖励Token SIL | H67: E_IN | I67: 外部生态 | J67: 外部生态—外部集成风险 | K67: 继承风险 | L67: 外部vFarm/FaaS升级改变奖励率参数，Iron与Value DeFi未同步识别配置变化 | M67: vFarm奖励参数异常 → SIL未来一年奖励提前领取 → SIL被抛售 → IRON相关LP受损；IRON稳定机制未被攻破 | N67: 不适用 | O67: IRON稳定机制未被直接击穿；主要市场影响是SIL抛售及IRON-SIL LP损失。 | P67: 约17万美元级SIL奖励被提前领取并抛售 | Q67: Iron停止SIL合作并迁移到STEEL，针对受影响SIL/LP用户安排补偿 | R67: E | S67: Iron官方post-mortem标题及补偿时间均指向2021-03-16；正文个别位置出现“2020”应视为笔误 | T67: 事件依据 | U67: 资产证明
A68: 64 | B68: 2022年6—7月 | C68: CoinFLEX／flexUSD：平台退出限制与兑付依赖 | D68: flexUSD | E68: CoinFLEX中心化平台 | F68: 中心化平台发行的收益型美元稳定币；兑付依赖CoinFLEX | G68: flexUSD是CoinFLEX平台流动性/对手方危机传导的稳定币 | H68: E_IN | I68: 外部生态 | J68: 外部生态—外部集成风险 | K68: 重塑风险 | L68: CoinFLEX暂停提现并出现大型对手方欠款，flexUSD兑付依赖的平台流动性随之失效 | M68: CoinFLEX提现暂停/对手方欠款 → flexUSD赎回能力下降 → 市场折价 → 平台重组与恢复安排 | N68: 是 | O68: 发生明显或持续性脱锚/折价，价格稳定性受到实质破坏；CoinFLEX对手方资金缺口从约4,700万美元扩大至约8,400万美元，flexUSD严重折价 | P68: CoinFLEX对手方资金缺口从约4,700万美元扩大至约8,400万美元，flexUSD严重折价 | Q68: CoinFLEX进入重组/债权处置，flexUSD长期折价并高度依赖平台恢复能力 | R68: E→C→M | T68: 事件依据 | U68: 资产证明
A69: 65 | B69: 2022-10-31—2022-11-02 | C69: Solend Protocol | D69: USDH | E69: Solana | F69: 加密资产超额抵押；Hubble发行USDH | G69: USDH是被操纵局部价格并作为高估抵押品使用的稳定币 | H69: E_IN | I69: 外部生态 | J69: 外部生态—外部集成风险 | K69: 继承风险 | L69: Solend对低流动性USDH市场使用即时spot price，缺乏足够TWAP/独立价格约束 | M69: 薄池USDH被拉高 → Solend读取异常spot价 → USDH抵押价值虚增 → 借走其他资产 → 隔离池坏账 | N69: 局部/短时 | O69: 出现局部或短时价格偏离，未观察到同等程度的全市场持续失稳；约100万—126万美元借贷坏账 | P69: 约100万—126万美元借贷坏账 | Q69: Solend隔离受影响池并在V2采用更保守spot/TWAP预言机设计 | R69: E | T69: 事件依据 | U69: 资产证明
A70: 66 | B70: 2023-03-13—2023-04-14 | C70: Euler 攻击冲击 Angle | D70: agEUR（现名 EURA；锚定 EUR） | E70: Ethereum | F70: 多抵押欧元稳定币；部分储备配置于Euler等DeFi | G70: agEUR是因储备配置于Euler而承受外部协议损失传染的稳定币 | H70: E_IN | I70: 外部生态 | J70: 外部生态—外部集成风险 | K70: 重塑风险 | L70: Angle将大量USDC储备部署在Euler，Euler被攻击后储备资产直接形成损失敞口 | M70: Euler被攻击 → Angle储备USDC受损 → agEUR偿付预期恶化 → 二级市场偏离 → 后续资本与风险管理修复 | N70: 是 | O70: agEUR出现风险传染后的市场偏离并随后修复；核心冲击来自Angle储备USDC在Euler的损失敞口。 | P70: Angle约1,760万USDC配置在Euler；Euler整体攻击规模约1.97亿美元 | Q70: Angle通过资本补充、风险参数和储备管理调整吸收Euler损失并恢复稳定运行 | R70: E→C→M | T70: 事件依据 | U70: 资产证明
A71: 67 | B71: 2023-04-13 | C71: Yearn旧iEarn yUSDT配置错误 | D71: yUSDT（USDT收益份额代币；Yearn旧iEarn） | E71: Ethereum | F71: 非独立稳定币；yUSDT代表Yearn旧iEarn中的USDT存款份额 | G71: yUSDT是代表用户USDT存款份额的收益型代币，并非独立稳定币 | H71: E_IN | I71: 外部生态 | J71: 外部生态—外部集成风险 | K71: 继承风险 | L71: 旧iEarn yUSDT部署时错误引用iUSDC地址，底层资产与份额会计长期不一致 | M71: 底层地址配置错误 → 份额/资产会计可被放大 → 异常yUSDT产生 → 换走DAI/USDC/USDT等资产 | N71: 不适用 | O71: 稳定币价格并非本案主要评价对象；主要影响体现为资产被盗、冻结/查扣、平台限制、违法利用或外围协议损失。 | P71: 约1,000万—1,160万美元稳定币资产被提取 | Q71: Yearn确认仅影响旧iEarn合约，主流V2不受影响；遗留系统进一步退役/隔离 | R71: E | T71: 事件依据 | U71: 资产证明
A72: 68 | B72: 2023-12-06—2023-12-07 | C72: Elephant Money BUSD BuyBack价格操纵 | D72: TRUNK生态外围BUSD BuyBack合约 | E72: BSC | F72: 储备／双Token机制；TRUNK与ELEPHANT生态联动 | G72: TRUNK生态受外围BUSD回购治理合约攻击影响，TRUNK本身未被再次无限铸造 | H72: E_IN | I72: 外部生态 | J72: 外部生态—外部集成风险 | K72: 重塑风险 | L72: BuyBack bot停机积累可提价值，外围合约又依赖可被闪电贷操纵的AMM现货状态 | M72: BuyBack余额积累 → 闪电贷操纵BUSD/WBNB状态 → sweep按失真价格执行 → 外围合约资产被提取 | N72: 不适用 | O72: TRUNK未出现由本次外围BuyBack事件导致的系统性脱锚；损失集中于BUSD回购治理合约。 | P72: 链上提取约16.5万美元；项目官方称影响约20万美元 | Q72: Elephant切断受影响BuyBack合约对Treasury的访问并修复自动运维/价格路径 | R72: E | S72: 攻击路径明确；链上提取约16.5万美元与项目称约20万美元属于损失口径差异 | T72: 事件依据 | U72: 资产证明
A73: 69 | B73: 2024-02-28 | C73: Seneca Protocol | D73: senUSD | E73: Arbitrum、Ethereum | F73: 加密资产抵押借贷；抵押品支持senUSD | G73: senUSD是Seneca借贷体系债务稳定币；被盗主体主要是外部抵押资产 | H73: E_IN | I73: 外部生态 | J73: 外部生态—外部集成风险 | K73: 继承风险 | L73: Chamber允许过宽外部调用，可借用用户已授予协议的ERC-20 allowance执行任意transferFrom | M73: Chamber任意外部调用 → 借用用户allowance → 抵押Token被转走 → Seneca损失并暂停 | N73: 否 | O73: senUSD未出现系统性脱锚；损失集中于Seneca用户抵押资产和协议授权边界。 | P73: 约640万美元抵押资产被转走 | Q73: Seneca暂停协议并要求撤销授权，项目后续基本停止正常运营 | R73: E | T73: 事件依据 | U73: 资产证明
A74: 70 | B74: 2024-06-10、2024-06-13 | C74: UwU Lend | D74: sUSDe | E74: Ethereum | F74: USDe质押收益Token；底层为delta-neutral合成美元 | G74: sUSDe是UwU用于抵押估值的外部收益资产，USDe机制本身未被攻破 | H74: E_IN | I74: 外部生态 | J74: 外部生态—外部集成风险 | K74: 继承风险 | L74: UwU把多个相关性很高且可操纵的Curve价格输入当作足够独立的抵押定价依据 | M74: Curve价格输入被操纵 → sUSDe抵押估值失真 → 异常借贷/清算 → UwU资产损失 → 二次攻击扩大损失 | N74: 不适用 | O74: USDe/sUSDe本身未出现由该攻击引发的系统性脱锚；主要表现为UwU借贷坏账和被盗资产损失。 | P74: 两轮攻击合计约2,300万美元损失 | Q74: UwU暂停、修复并推进赔付/追偿；第二轮攻击暴露首次修复不完整 | R74: E | S74: 攻击交易与多家安全机构复盘一致；底层USDe/sUSDe本身未被攻破 | T74: 事件依据 | U74: 资产证明
A75: 71 | B75: 2025/2/24 | C75: Infini：残留管理权限提取USDC | D75: USDC为金库资产；DAI为后续兑换资产 | E75: Ethereum／Infini金库 | F75: 法币储备型稳定币或其外部使用/处置场景 | G75: USDC是Infini金库中因残留管理权限被直接提取的主要资产 | H75: E_IN | I75: 外部生态 | J75: 外部生态—外部集成风险 | K75: 继承风险 | L75: Infini旧开发者/管理员权限未彻底撤销，残留特权可直接提取金库USDC | M75: 残留管理员权限 → 直接提取约4950万USDC → 换成DAI/其他资产 → 金库巨额损失 | N75: 不适用 | O75: USDC未脱锚；核心表现为Infini金库约4950万美元资产被提取。 | P75: 约4,950万美元USDC被提取 | Q75: Infini确认巨额金库损失并追踪攻击者，残留权限管理成为核心整改点 | R75: E | T75: 事件依据 | U75: 资产证明
A76: 72 | B76: 2025-03-21 08:46—09:01 UTC | C76: Zoth：USD0++储备金库被恶意升级 | D76: USD0++为被盗储备/抵押资产；DAI为兑换路径 | E76: Ethereum／Zoth金库 | F76: USD0++为RWA收益型稳定资产；本案是外部Zoth金库持仓 | G76: USD0++是Zoth金库中被恶意升级合约转走的储备/抵押资产 | H76: E_IN | I76: 外部生态 | J76: 外部生态—外部集成风险 | K76: 继承风险 | L76: Zoth部署者/管理员权限失陷后，代理金库被upgradeToAndCall替换为恶意实现 | M76: 管理员权限失陷 → 金库恶意升级 → 约885万USD0++转走 → 换成DAI/ETH → 储备资产损失 | N76: 不适用 | O76: USD0++未因Zoth金库攻击发生系统性锚定失效；主要表现为储备资产被盗。 | P76: 约885万USD0++被转走，损失约840万美元 | Q76: Zoth金库被恶意升级并损失USD0++；项目暂停/处置受影响金库并追踪攻击资金 | R76: E | T76: 事件依据 | U76: 资产证明
A77: 73 | B77: 2025/3/25 | C77: Abracadabra：GM Cauldrons抵押状态攻击 | D77: MIM；GM仓位为外部抵押资产 | E77: Arbitrum／GMX V2集成 | F77: 加密资产超额抵押；Cauldron抵押借出MIM | G77: MIM是GM抵押状态攻击后无充分抵押借出的稳定币 | H77: E_IN | I77: 外部生态 | J77: 外部生态—外部集成风险 | K77: 重塑风险 | L77: GM Cauldron对外部GM仓位/抵押状态的同步假设被破坏，使抵押状态可被攻击者错配 | M77: 外部GM仓位状态被操纵/错配 → Cauldron高估抵押 → 约1340万MIM无充分抵押借出 → 协议坏账 | N77: 否 | O77: 未观察到有证据支持的系统性脱锚；主要影响体现为供应、储备、资金损失、兑付或服务可用性变化。 | P77: 约1,340万MIM在不足额抵押条件下被借出 | Q77: Abracadabra隔离GM Cauldrons并修复集成状态逻辑，MIM供应和坏账进入处置 | R77: E→C | T77: 事件依据 | U77: 资产证明
A78: 74 | B78: 2025/6/18 | C78: Nobitex：多资产破坏攻击中的美元稳定币 | D78: 美元稳定币包含在多资产损失中 | E78: Nobitex多链交易所 | F78: 法币储备型稳定币或其外部使用/处置场景 | G78: 美元稳定币是Nobitex多资产破坏性转移的一部分，并非攻击根因 | H78: E_IN | I78: 外部生态 | J78: 外部生态—外部集成风险 | K78: 继承风险 | L78: 攻击者获得Nobitex关键权限后把多类资产转至推定不可用地址，稳定币只是受损资产之一 | M78: 关键权限/基础设施被攻陷 → 多资产转入不可用地址 → 稳定币余额同步损失 → 平台服务受创 | N78: 不适用 | O78: 稳定币未因Nobitex攻击发生协议级脱锚；它们只是多资产破坏性转移的一部分。 | P78: 超过9,000万美元多类加密资产被转至推定不可用地址，其中包含美元稳定币 | Q78: Nobitex遭重大破坏性攻击并暂停服务，稳定币损失作为多资产损失的一部分处理 | R78: E | T78: 事件依据 | U78: 资产证明
A79: 75 | B79: 2025-06-30公告；2025—2026持续退出 | C79: Kujira USK：Rujira合并中的仅还款退出 | D79: USK | E79: Kujira→Rujira／THORChain迁移 | F79: 加密资产超额抵押；USK抵押债务体系 | G79: USK是Kujira并入Rujira过程中进入仅还款收缩的稳定币 | H79: E_IN | I79: 外部生态 | J79: 外部生态—外部集成风险 | K79: 重塑风险 | L79: Kujira生态并入Rujira/THORChain后，USK停止扩张并转为仅还款收缩 | M79: 生态合并 → USK停止新增借款 → 利率/还款机制推动债务回收 → USK逐步销毁退出 | N79: 否 | O79: USK按repayment-only方式收缩，没有发生由该退出安排直接引发的系统性脱锚。 | P79: 无攻击损失；USK逐步转为仅还款、债务收缩状态 | Q79: USK在Rujira合并中进入repayment-only阶段，债务偿还后相应Token逐步销毁 | R79: E→C | T79: 事件依据 | U79: 资产证明
A80: 76 | B80: 2025-11-06 | C80: Elixir deUSD：对Stream敞口与赎回基础设施关闭 | D80: Elixir deUSD／sdeUSD | E80: Elixir发行体系＋Morpho/Stream信用敞口 | F80: 合成美元；抵押/对冲结构并包含对Stream的信用敞口 | G80: deUSD是因对Stream信用敞口及赎回安排关闭而进入退出的稳定币 | H80: E_IN | I80: 外部生态 | J80: 外部生态—外部集成风险 | K80: 重塑风险 | L80: deUSD支持资产中对Stream的信用敞口高度集中，Stream危机使应收债权难以及时转化为兑付现金 | M80: Stream信用事件 → deUSD支持资产流动性受限 → 大量赎回 → 关闭mint/redeem → 快照并按USDC安排退出 | N80: 局部/短时 | O80: 出现局部或短时价格偏离，未观察到同等程度的全市场持续失稳；Elixir对Stream信用敞口约6,800万美元；deUSD进入sunset并安排剩余持有人USDC兑付 | P80: Elixir对Stream信用敞口约6,800万美元；deUSD进入sunset并安排剩余持有人USDC兑付 | Q80: Elixir停止deUSD，完成快照并计划对剩余持有人按1:1 USDC处理退出 | R80: E→C→M | S80: Elixir公开sunset/兑付安排及对Stream敞口规模 | T80: 事件依据 | U80: 资产证明
A81: 77 | B81: 2026/1/30 | C81: Gyroscope：跨链回调授权转走GYD | D81: GYD | E81: Arbitrum→Ethereum跨链路径 | F81: 资产支持型稳定币GYD；事件发生于跨链回调/授权 | G81: GYD是跨链回调错误授权后被攻击者转走的稳定币 | H81: E_IN | I81: 外部生态 | J81: 外部生态—外部集成风险 | K81: 继承风险 | L81: 跨链回调对外部调用授予过宽Token allowance，攻击者借回调路径转走GYD | M81: 跨链回调授权过宽 → 攻击者获得无限GYD allowance → 约609.9万GYD转走 → 跨链换出 | N81: 否 | O81: GYD未以系统性脱锚为主要后果；核心是跨链授权漏洞导致约609.9万GYD被转走。 | P81: 约609.9万GYD被转走；可实际变现的流动性约80万美元级 | Q81: Gyroscope暂停/修复相关跨链流程并追踪被盗GYD，可变现损失受市场流动性限制 | R81: E | T81: 事件依据 | U81: 资产证明
A82: 78 | B82: 2026-02-22 | C82: YieldBlox：USTRY价格/预言机操纵后借出USDC/XLM | D82: USDC为借出资产；USTRY为被操纵抵押资产（非稳定币） | E82: Stellar／Blend V2 YieldBlox池 | F82: USDC外部借贷场景；USTRY为代币化国债抵押品 | G82: USDC是被借走的现金类资产；USTRY才是遭预言机操纵的抵押品 | H82: E_IN | I82: 外部生态 | J82: 外部生态—外部集成风险 | K82: 继承风险 | L82: 极薄USTRY/USDC市场使单笔异常成交主导VWAP，YieldBlox缺乏流动性门槛和独立价格校验 | M82: USTRY薄池成交被操纵 → VWAP升至约106美元 → 抵押品高估 → 借出XLM/USDC → YieldBlox坏账 | N82: 不适用 | O82: USDC未失去锚定；损失来自YieldBlox错误高估USTRY后借出USDC/XLM。 | P82: 损失约1,020万—1,086万美元，包括约100万USDC及6,125万XLM借出 | Q82: YieldBlox/Blend受影响池产生巨额坏账，事件推动对薄市场预言机配置的重新审查 | R82: E | S82: BlockSec等技术复盘支持；USTRY是被操纵抵押资产，USDC只是借出资产 | T82: 事件依据 | U82: 资产证明
A83: 79 | B83: 2026-03-02 | C83: Curve LlamaLend：sDOLA捐赠与硬清算 | D83: sDOLA为抵押份额；crvUSD为贷款/清算资产 | E83: Ethereum／Curve LlamaLend | F83: crvUSD为借贷稳定币；sDOLA为外部抵押份额Token | G83: crvUSD是LlamaLend贷款/清算资产；sDOLA是被捐赠操纵的抵押份额 | H83: E_IN | I83: 外部生态 | J83: 外部生态—外部集成风险 | K83: 继承风险 | L83: 攻击者直接向sDOLA金库捐赠DOLA抬高每份share价值，LlamaLend据此高估抵押品 | M83: 向sDOLA直接捐赠 → share价值虚高 → LlamaLend抵押估值上升 → 借款/硬清算 → 借款人权益损失 | N83: 不适用 | O83: crvUSD未发生系统性脱锚；核心是sDOLA估值被抬高后触发借贷和清算损失。 | P83: 攻击者收益约24万美元；借款人权益损失约82.2万crvUSD | Q83: Curve/相关协议处置sDOLA市场风险，捐赠攻击导致借款人被硬清算并产生权益损失 | R83: E | S83: 公开技术复原支持donation attack；部分损失口径来自研究机构估算 | T83: 事件依据 | U83: 资产证明
A84: 80 | B84: 2026-05-29准备；2026-06-01执行 | C84: GnosisPay：签名验证绕过转走EURe/USDC.e | D84: EURe、USDC.e（另含少量xDAI、USDC、USDT） | E84: Gnosis Pay／Safe钱包基础设施 | F84: 法币支持稳定币支付资产；本案发生于支付钱包基础设施 | G84: EURe和USDC.e是支付钱包签名验证绕过后被盗的主要稳定币资产 | H84: E_IN | I84: 外部生态 | J84: 外部生态—外部集成风险 | K84: 继承风险 | L84: ERC-1271签名验证实现存在绕过路径，攻击者可伪造支付钱包授权 | M84: 签名验证绕过 → 伪造Safe授权 → EURe/USDC.e等资产转出 → 攻击者换币洗出 | N84: 不适用 | O84: EURe/USDC.e未发生系统性脱锚；核心是支付钱包资产被盗。 | P84: 约150万美元资产被盗，其中EURe约45.3万美元、USDC.e约39.9万美元 | Q84: Gnosis Pay修复签名验证、处置受影响钱包并推进用户补偿/资产追踪 | R84: E | T84: 事件依据 | U84: 资产证明
A85: 81 | B85: 2026-06-20 | C85: MainStreet msUSD：验证服务终止后的价格偏离 | D85: msUSD | E85: Ethereum及相关DeFi市场 | F85: RWA/信用资产支持的msUSD；依赖第三方储备验证 | G85: msUSD是第三方储备验证服务终止后出现严重折价的稳定币 | H85: E_IN | I85: 外部生态 | J85: 外部生态—外部集成风险 | K85: 重塑风险 | L85: 第三方Accountable储备验证服务终止，市场难以及时确认msUSD支持资产，引发信任与流动性冲击 | M85: 储备验证服务终止 → 透明度和信心下降 → 二级市场抛售/流动性萎缩 → msUSD跌至约0.25–0.30 | N85: 是 | O85: 发生明显或持续性脱锚/折价，价格稳定性受到实质破坏；msUSD一度跌至约0.25—0.30美元 | P85: msUSD一度跌至约0.25—0.30美元 | Q85: msUSD严重折价后市场信任与流动性受损，储备验证依赖成为主要治理问题 | R85: E→M | S85: 严重价格折价与验证服务终止可核；公开一手技术/储备细节有限 | T85: 事件依据 | U85: 资产证明
A86: 82 | B86: 2026/7/16 | C86: DeFiTuna：薄池路径和价值舍入绕过偿付检查 | D86: USDC | E86: Solana／DeFiTuna | F86: 法币储备型稳定币或其外部使用/处置场景 | G86: USDC是DeFiTuna薄池/舍入攻击中被借出的资产 | H86: E_IN | I86: 外部生态 | J86: 外部生态—外部集成风险 | K86: 继承风险 | L86: 薄流动性池路径与价值舍入共同让偿付检查高估仓位，从而借出USDC | M86: 薄池/舍入操纵 → 仓位价值被高估 → 借出约57万USDC → DeFiTuna产生坏账 | N86: 不适用 | O86: USDC未脱锚；核心是DeFiTuna产生约57万美元借贷损失。 | P86: 约57万美元USDC被借走 | Q86: DeFiTuna隔离受影响市场并修复定价/偿付检查，USDC坏账进入处置 | R86: E | T86: 事件依据 | U86: 资产证明
A87: 83 | B87: 2026-08-27 02:01:02—02:21:12 UTC；8月28日恢复 | C87: ICON迁移消息重放与bnUSD处置 | D87: bnUSD为重复释放资产；USDC为后续借贷资产 | E87: ICON迁移基础设施 | F87: 加密资产超额抵押稳定币bnUSD；本案发生于迁移基础设施 | G87: bnUSD是迁移消息重放中被重复释放的稳定币；USDC为后续借贷资产 | H87: E_IN | I87: 外部生态 | J87: 外部生态—外部集成风险 | K87: 继承风险 | L87: 迁移消息缺少充分一次性消费/重放保护，同一迁移指令可被重复执行释放资产 | M87: 迁移消息重放 → ICX与bnUSD被重复释放 → 基金会迁移资产损失 → 网络暂停/修复后恢复 | N87: 不适用 | O87: bnUSD并非主要价格风险对象；迁移合约异常释放后基金会处置并恢复服务。 | P87: 重复释放约119.866M ICX及531,600 bnUSD | Q87: ICON基金会暂停迁移/网络相关功能并修复重放问题，8月28日恢复服务 | R87: E | S87: ICON官方复盘支持重放机制、数量和恢复时间 | T87: 事件依据 | U87: 资产证明
A88: 84 | B88: 2026-08-28 | C88: Rain：共享稳定币卡合约授权绕过 | D88: Solana USDC、USDT卡余额／抵押资产 | E88: Solana稳定币卡合约；资金后续跨至Ethereum | F88: 法币储备型稳定币或其外部使用/处置场景 | G88: USDC/USDT是稳定币卡用户余额，被外围支付合约授权漏洞转走 | H88: E_IN | I88: 外部生态 | J88: 外部生态—外部集成风险 | K88: 继承风险 | L88: 共享稳定币卡合约授权边界被绕过，攻击者可动用用户已存入的USDC/USDT余额 | M88: 卡合约授权绕过 → 用户USDC/USDT余额被提取 → 跨链换币/洗出 → 支付服务侧损失 | N88: 不适用 | O88: USDC/USDT本身未脱锚；用户稳定币卡余额因外围授权漏洞被盗。 | P88: 约110万美元USDC/USDT等资产被盗 | Q88: Rain及相关服务方修复授权路径、追踪资产并强化稳定币卡合约监控 | R88: E | T88: 事件依据 | U88: 资产证明
A89: 85 | B89: 2026-09-02—2026-09-07 | C89: Cozy保护市场虚假触发后提取USDC.e | D89: USDC.e | E89: Optimism／Cozy保护市场 | F89: 法币储备型稳定币或其外部使用/处置场景 | G89: USDC.e是Cozy保护市场错误认定保险事件后的赔付资产 | H89: E_IN | I89: 外部生态 | J89: 外部生态—外部集成风险 | K89: 继承风险 | L89: Optimistic Oracle的争议/挑战活性不足，虚假保险事故声明在无人有效挑战时生效 | M89: 提交虚假保险事故YES结果 → 挑战窗口无人有效反对 → 赔付条件生效 → USDC.e被领取 | N89: 不适用 | O89: USDC.e未脱锚；错误保险赔付导致外围协议资产流失。 | P89: 约16万—17万美元USDC.e被异常领取 | Q89: Cozy相关保护市场被错误触发后暴露Oracle争议机制活性不足，事件推动治理/挑战机制复核 | R89: E | S89: 链上安全复原和行业资料支持；未找到Cozy完整最终技术报告 | T89: 事件依据 | U89: 资产证明
A90: 86 | B90: 2026-09-03—2026-09-04 UTC | C90: Notional V1遗留Escrow漏洞导致USDC/DAI被提取 | D90: USDC、DAI | E90: Ethereum／Notional V1 Escrow | F90: 法币储备型稳定币或其外部使用/处置场景 | G90: USDC/DAI是Notional遗留Escrow漏洞中被提取的资产 | H90: E_IN | I90: 外部生态 | J90: 外部生态—外部集成风险 | K90: 继承风险 | L90: 已废弃V1仍保留资产和提款入口，整数/抵押检查边界漏洞可构造异常债务状态 | M90: 遗留V1漏洞 → 构造异常债务/抵押状态 → Escrow释放USDC/DAI → 约172万美元资产被盗 | N90: 不适用 | O90: USDC/DAI未脱锚；核心是遗留Notional V1合约释放稳定币资产造成损失。 | P90: 约165万USDC和6.9万DAI被盗，合计约172万美元级 | Q90: Notional确认V1遗留合约攻击并暴露退役资产管理不足，后续修复/追踪被盗稳定币 | R90: E | T90: 事件依据 | U90: 资产证明
A91: 87 | B91: 2018-01—2021-09 | C91: 郭某钊等：泰达币中介的非法换汇 | D91: USDT | E91: 中国境内外／USDT交易平台 | F91: 法币储备型稳定币或其外部使用/处置场景 | G91: USDT是非法换汇中连接境外外币和境内人民币兑付的桥梁资产 | H91: E_IU | I91: 外部生态 | J91: 外部生态—违法利用风险 | K91: 重塑风险 | L91: 中介利用USDT连接境外外币入金与境内人民币兑付，绕开持牌外汇体系 | M91: 境外外币进入中介 → USDT链上转移 → 境内人民币对敲兑付 → 非法经营/换汇责任追究 | N91: 不适用 | O91: USDT未脱锚；核心表现为非法换汇规模、账户/地址证据和刑事责任。 | P91: 非法换汇规模超过2.2亿元人民币，其中接收超过600万USDT | Q91: 案件经刑事起诉/裁判处理，USDT中介型非法换汇被明确纳入违法经营认定 | R91: E | T91: 事件依据 | U91: 资产证明
A92: 88 | B92: 2019—2025；2025-03-06—03-07执法行动 | C92: Garantex：持续非法金融指控与平台查封 | D92: USDT为主要兑换媒介；执法处置另含多种加密资产 | E92: Garantex交易平台基础设施＋链上稳定币地址 | F92: 法币储备型稳定币或其外部使用/处置场景 | G92: USDT是Garantex客户兑换和执法冻结中的主要结算资产 | H92: E_IU | I92: 外部生态 | J92: 外部生态—违法利用风险 | K92: 继承风险 | L92: Garantex长期被指为违法资金转换平台，执法机构查封基础设施并协同冻结稳定币 | M92: Garantex违法资金服务 → 制裁/执法升级 → 服务器与域名查封、USDT冻结 → 平台业务中断 | N92: 不适用 | O92: USDT价格不是核心风险指标；主要表现为Garantex业务停摆、地址冻结和执法查封。 | P92: 约2,300万—2,800万美元USDT被冻结；联合执法另查封/冻结超过2,600万美元加密资产 | Q92: Garantex基础设施被查封、部分资金冻结，相关人员/业务随后向替代平台迁移 | R92: E | T92: 事件依据 | U92: 资产证明
A93: 89 | B93: 2021-08—2025-01涉及活动；2025-05-01认定；2025-10-14最终规则 | C93: Huione：稳定币通道与美国金融系统限制 | D93: USDT为结算工具；USDH为平台宣称的新稳定币通道 | E93: Huione集团／美国金融系统 | F93: 法币储备型稳定币或其外部使用/处置场景 | G93: USDT是Huione生态结算工具；USDH是其宣称的替代稳定币通道 | H93: E_IU | I93: 外部生态 | J93: 外部生态—违法利用风险 | K93: 重塑风险 | L93: Huione被指长期为诈骗和洗钱网络提供结算服务，美国监管最终切断其接入美国金融系统 | M93: 高风险结算网络扩大 → 美国监管认定洗钱风险 → 禁止美国金融机构相关往来 → 稳定币通道受限 | N93: 不适用 | O93: 稳定币锚定不是核心；主要表现为Huione被切断美国金融系统接入与合规压力升级。 | P93: FinCEN称Huione在2021—2025年间至少处理约40亿美元违法所得 | Q93: FinCEN最终规则切断Huione接入美国金融系统，相关稳定币结算网络受限 | R93: E | T93: 事件依据 | U93: 资产证明
A94: 90 | B94: 约2022—2025；2025-03判决、2025-07-16披露 | C94: 上海浦东：稳定币媒介的跨境非法换汇案 | D94: USDT | E94: 上海／跨境对敲网络 | F94: 法币储备型稳定币或其外部使用/处置场景 | G94: USDT是跨境对敲和非法换汇网络的结算媒介 | H94: E_IU | I94: 外部生态 | J94: 外部生态—违法利用风险 | K94: 重塑风险 | L94: 团伙以USDT等稳定币进行境内外对敲，在不同司法辖区完成非法换汇 | M94: 境外资金与USDT对敲 → 境内人民币支付 → 规避外汇管制 → 刑事判决与资金追缴 | N94: 不适用 | O94: USDT未脱锚；核心表现为约65亿元人民币非法外汇对敲与司法处罚。 | P94: 非法买卖外汇规模约65亿元人民币 | Q94: 上海法院对非法换汇链条作出判决，稳定币对敲模式成为司法认定的重要事实 | R94: E | S94: 判决与约65亿元规模可核；公开材料对三年业务窗口的精确起止日披露有限 | T94: 事件依据 | U94: 资产证明
A95: 91 | B95: 2023-11-20（自愿冻结）；2025-06-18（起诉公开） | C95: DOJ USDT 诈骗资金民事没收案 | D95: USDT（Ethereum，文书 Token Groups A–G） | E95: Ethereum／OKX链下账户记录／司法程序 | F95: 法币储备型稳定币或其外部使用/处置场景 | G95: USDT是诈骗资金分层转移、冻结和民事没收的价值载体 | H95: E_IU | I95: 外部生态 | J95: 外部生态—违法利用风险 | K95: 重塑风险 | L95: 大规模投资诈骗将受害资金通过多地址和交易所账户分层转移，并最终集中为USDT | M95: 诈骗受害资金进入加密网络 → 多地址分层 → Tether协助冻结 → DOJ民事没收约2.25亿USDT | N95: 不适用 | O95: 稳定币价格并非本案主要评价对象；主要影响体现为资产被盗、冻结/查扣、平台限制、违法利用或外围协议损失。 | P95: 民事没收标的约225,364,961 USDT，涉及430多名疑似受害者 | Q95: 相关USDT已被冻结/查扣并进入美国民事没收程序，案件继续按司法程序处理 | R95: E | T95: 事件依据 | U95: 资产证明
A96: 92 | B96: 2023相关行为；2024-12-04制裁 | C96: TGR网络：USDT换现与OFAC制裁 | D96: USDT | E96: 跨境USDT与现金网络 | F96: 法币储备型稳定币或其外部使用/处置场景 | G96: USDT是现金换现和跨境资金安排中的结算媒介 | H96: E_IU | I96: 外部生态 | J96: 外部生态—违法利用风险 | K96: 重塑风险 | L96: TGR网络组织现金与USDT之间的跨境兑换，为受制裁或高风险主体提供金融通道 | M96: 现金与USDT兑换网络运作 → 跨境/受制裁资金流转 → OFAC制裁 → 相关地址与主体金融可用性下降 | N96: 不适用 | O96: USDT未脱锚；核心表现为现金—稳定币结算网络被识别、制裁和资产追踪。 | P96: 相关执法行动逮捕84人并扣押超过2,000万英镑现金与加密资产 | Q96: 相关个人/实体被OFAC制裁，稳定币地址和现金渠道成为执法监控重点 | R96: E | T96: 事件依据 | U96: 资产证明
A97: 93 | B97: 2024-07—2026-02平台活动；2026-08-07制裁 | C97: Shelbit相关USDT流转与2026年制裁 | D97: USDT等美元稳定币 | E97: Tron为主的稳定币结算网络 | F97: 法币储备型稳定币或其外部使用/处置场景 | G97: USDT等稳定币是Shelbit相关制裁规避和结算网络中的主要资产 | H97: E_IU | I97: 外部生态 | J97: 外部生态—违法利用风险 | K97: 重塑风险 | L97: 受制裁相关平台利用稳定币高流动性和跨境可转移性进行结算，形成链上制裁规避通道 | M97: 平台聚合稳定币流量 → 高风险/受制裁主体使用 → OFAC制裁与链上归因 → 结算通道被限制 | N97: 不适用 | O97: 稳定币价格并非本案主要评价对象；主要影响体现为资产被盗、冻结/查扣、平台限制、违法利用或外围协议损失。 | P97: TRM追踪相关网络累计流量超过63亿美元，约88%涉及Tron上的美元稳定币活动 | Q97: 相关主体被OFAC制裁，稳定币服务商与交易平台面临筛查、冻结和拒绝服务义务 | R97: E | S97: OFAC支持制裁事实；63亿美元及88%稳定币比例来自TRM链上归因口径 | T97: 事件依据 | U97: 资产证明
A98: 94 | B98: 2024-07—2026-04（终审） | C98: 杭州：黄金换U币诈骗案终审 | D98: USDT | E98: 杭州／跨境USDT地址网络 | F98: 法币储备型稳定币或其外部使用/处置场景 | G98: USDT是黄金诈骗所得变现并向境外转移的链上价值载体 | H98: E_IU | I98: 外部生态 | J98: 外部生态—违法利用风险 | K98: 重塑风险 | L98: 诈骗团伙将受害者资金先转化为黄金，再变现为USDT向境外地址转移 | M98: 投资诈骗 → 受害者交付黄金 → 黄金变现 → 兑换USDT → 境外地址转移 → 刑事追责 | N98: 不适用 | O98: 稳定币价格并非本案主要评价对象；主要影响体现为资产被盗、冻结/查扣、平台限制、违法利用或外围协议损失。 | P98: 受害人多次交付黄金，赃款部分兑换USDT跨境转移；案件已完成终审处置 | Q98: 案件完成二审/终审处置，黄金+USDT多层资金路径被司法机关认定并用于定罪 | R98: E | T98: 事件依据 | U98: 资产证明
A99: 95 | B99: 2024-11-21（交易及暴力事件）；2025-04-28（侦办报道）；2025-05-07（起诉） | C99: 台中：泰达币场外兑换纠纷与暴力案件 | D99: USDT | E99: 台中／USDT场外交易 | F99: 法币储备型稳定币或其外部使用/处置场景 | G99: USDT是场外兑换、疑似洗钱及后续暴力纠纷中的交易资产 | H99: E_IU | I99: 外部生态 | J99: 外部生态—违法利用风险 | K99: 重塑风险 | L99: 场外USDT兑换与疑似洗钱交易发生纠纷，线下交易关系进一步演变为暴力犯罪 | M99: 场外USDT兑换 → 交易/资金归属争议 → 暴力拘禁/索款 → 警方侦办并逮捕相关人员 | N99: 不适用 | O99: USDT未脱锚；核心是OTC交易、疑似洗钱和线下人身/财产风险。 | P99: 约20万USDT／约600万元新台币场外交易引发纠纷，警方逮捕15人 | Q99: 警方报道逮捕15人；检方于2025-05-07披露起诉10人，另有1人另案起诉、4名少年由少年法庭调查；事件作为USDT场外交易与线下暴力/洗钱风险案例处理 | R99: E | S99: 公视报道支持侦办时间、交易金额和逮捕人数；中央社转述台中地检署说明，支持2024-11-21行为日期与2025-05-07起诉情况；未取得判决文书。 | T99: 事件依据 | U99: 资产证明
A100: 96 | B100: 2025-03-21认罪；2025-03-27民事没收公告 | C100: Gotbit市场操纵所得USDT／USDC民事没收 | D100: USDT、USDC | E100: 非托管钱包＋美国司法程序 | F100: 法币储备型稳定币或其外部使用/处置场景 | G100: USDT/USDC是Gotbit市场操纵所得最终持有并被司法没收的资产 | H100: E_IU | I100: 外部生态 | J100: 外部生态—违法利用风险 | K100: 继承风险 | L100: Gotbit涉嫌市场操纵所得最终以USDT/USDC等加密资产保存在可识别钱包中 | M100: 市场操纵/欺诈所得 → 资金沉淀为USDT/USDC → DOJ追踪并控制资产 → 民事没收 | N100: 不适用 | O100: 稳定币价格并非本案主要评价对象；主要影响体现为资产被盗、冻结/查扣、平台限制、违法利用或外围协议损失。 | P100: 民事没收规模约2,300万美元，主要为USDT和USDC | Q100: Gotbit及创始人认罪，公司停止运营，相关USDT/USDC进入民事没收程序 | R100: E | T100: 事件依据 | U100: 资产证明
A101: 97 | B101: 2025-03后迁移；2025-08-14制裁披露 | C101: Grinex／A7A5：受制裁通道迁移与新制裁 | D101: A7A5（Old Vector发行，卢布支持） | E101: Grinex／Garantex／Old Vector；多链稳定币网络 | F101: 卢布支持稳定资产A7A5；与受制裁交易平台结算网络结合 | G101: A7A5是Garantex受打击后用于迁移余额和继续结算的卢布稳定资产 | H101: E_IU | I101: 外部生态 | J101: 外部生态—违法利用风险 | K101: 重塑风险 | L101: Garantex受打击后相关人员迁移至Grinex，并以A7A5重建受制裁结算与客户余额通道 | M101: Garantex受打击 → 客户余额迁移至Grinex/A7A5 → 新制裁与链上追踪 → 替代网络继续承压 | N101: 不适用 | O101: A7A5/USDT价格稳定性不是案件核心；主要表现为受制裁结算网络迁移和再次被制裁。 | P101: Grinex/A7A5承接Garantex迁移后形成数十亿美元级交易活动，并被进一步制裁 | Q101: Grinex及相关A7A5实体被进一步制裁，链上活动持续受到监测与限制 | R101: E | S101: OFAC/Chainalysis支持Grinex-A7A5迁移关系；具体客户余额迁移规模采用公开链上分析口径 | T101: 事件依据 | U101: 资产证明
A102: 98 | B102: 2025-04—05采购；2026-01-16披露 | C102: 伊朗央行USDT采购网络 | D102: USDT（Tron→Ethereum跨链路径） | E102: Tron→Ethereum跨链路径＋Nobitex | F102: 法币储备型稳定币或其外部使用/处置场景 | G102: USDT是伊朗央行被归因采购及跨链流转的美元价值载体 | H102: E_IU | I102: 外部生态 | J102: 外部生态—违法利用风险 | K102: 重塑风险 | L102: 受制裁中央银行难以使用传统美元清算体系，转而采购USDT并通过交易所/跨链网络流转 | M102: 央行采购USDT → Nobitex等渠道分发 → 跨链转移 → 规避传统美元结算限制并形成可追踪制裁风险 | N102: 不适用 | O102: 稳定币价格并非本案主要评价对象；主要影响体现为资产被盗、冻结/查扣、平台限制、违法利用或外围协议损失。 | P102: Elliptic归因至少5.07亿美元USDT由伊朗央行相关钱包网络采购/流转 | Q102: 相关钱包被链上分析机构持续追踪，稳定币通道面临发行方冻结和制裁执法风险 | R102: E | S102: 5.07亿美元为Elliptic基于泄露文件与链上归因的下限估计，并非伊朗央行官方披露 | T102: 事件依据 | U102: 资产证明
...

Sheet 来源
A2: 案件来源与资产证明 | B2: 案件来源与资产证明
A4: 序号 | B4: 事件/稳定币 | C4: 事件依据 | D4: 资产证明 | E4: 补充来源 | F4: 资产证明说明
A5: 1 | B5: Tether储备披露处罚/USDT | C5: 事件依据 | D5: 资产证明 | F5: 独立资产/官方证明
A6: 2 | B6: Tether储备调查和解/USDT | C6: 事件依据 | D6: 资产证明 | F6: 独立资产/官方证明
A7: 3 | B7: BitShares全局清算/bitUSD | C7: 事件依据 | D7: 资产证明 | F7: 事件来源兼资产证明
A8: 4 | B8: TrueCoin储备披露争议/TUSD | C8: 事件依据 | D8: 资产证明 | F8: 独立官方资产/产品证明
A9: 5 | B9: Neutrino多次脱锚/USDN | C9: 事件依据 | D9: 资产证明 | F9: 事件来源兼资产证明
A10: 6 | B10: NEAR资产缺口退出/USN | C10: 事件依据 | D10: 资产证明 | F10: 事件来源兼资产证明
A11: 7 | B11: Neutrino失稳转型/USDN | C11: 事件依据 | D11: 资产证明 | F11: 事件来源兼资产证明
A12: 8 | B12: Circle储备银行危机/USDC | C12: 事件依据 | D12: 资产证明 | F12: 独立资产/官方证明
A13: 9 | B13: Tangible兑付缺口/USDR | C13: 事件依据 | D13: 资产证明 | F13: 独立官方资产/产品证明
A14: 10 | B14: Inter Protocol停止运行/IST | C14: 事件依据 | D14: 资产证明 | F14: 独立资产/官方证明
A15: 11 | B15: Mountain有序退出/USDM | C15: 事件依据 | D15: 资产证明 | F15: 独立资产/官方证明
A16: 12 | B16: Paxos停止发行迁移/USDL | C16: 事件依据 | D16: 资产证明 | F16: 独立资产/官方证明
... A22: 18 | B22: Mochi特权信用扩张/USDM | C22: 事件依据 | D22: 资产证明 | F22: 事件来源兼资产证明
A23: 19 | B23: Elephant储备攻击/TRUNK | C23: 事件依据 | D23: 资产证明 | E23: https://crypto.training/hacks/2022-04-elephant_money/ | F23: 第二来源兼资产证明
A24: 20 | B24: Beanstalk闪贷治理/BEAN | C24: 事件依据 | D24: 资产证明 | F24: 独立官方资产/产品证明
A25: 21 | B25: Linear发行权限失陷/lUSD | C25: 事件依据 | D25: 资产证明 | E25: https://www.theblock.co/post/252408/linear-finance-reports-attack-that-drained-linear-usd-liquidity-on-pancakeswap-and-ascendex | F25: 第二来源兼资产证明
A26: 22 | B26: Resolv异常铸造/USR | C26: 事件依据 | D26: 资产证明 | F26: 独立资产/官方证明
A27: 23 | B27: StablR未授权增发/USDR·EURR | C27: 事件依据 | D27: 资产证明 | F27: 独立官方资产/产品证明
A28: 24 | B28: Origin重入异常铸币/OUSD | C28: 事件依据 | D28: 资产证明 | F28: 独立官方资产/产品证明
A29: 25 | B29: Haven验证漏洞增发/xUSD | C29: 事件依据 | D29: 资产证明 | E29: https://havenprotocol.org/2021/07/16/hard-fork-rollback/ | F29: 第二来源兼资产证明
A30: 26 | B30: SafeDollar奖励计算漏洞/SDO | C30: 事件依据 | D30: 资产证明 | F30: 事件来源兼资产证明
A31: 27 | B31: Cashio伪造抵押铸币/CASH | C31: 事件依据 | D31: 资产证明 | F31: 事件来源兼资产证明
A32: 28 | B32: Nirvana价格曲线操纵/NIRV | C32: 事件依据 | D32: 资产证明 | F32: 事件来源兼资产证明
A33: 29 | B33: Acala奖励配置增发/aUSD | C33: 事件依据 | D33: 资产证明 | F33: 事件来源兼资产证明
A34: 30 | B34: Abracadabra旧价自清算/MIM | C34: 事件依据 | D34: 资产证明 | E34: https://blocksecteam.medium.com/beyond-the-market-risk-a-logic-bug-identified-in-sushiswaps-kashipairmediumriskv1-contract-80ead49d8d6d | F34: 独立资产/官方证明
A35: 31 | B35: Defrost管理员权限攻击/H2O | C35: 事件依据 | D35: 资产证明 | E35: https://www.coindesk.com/business/2022/12/26/defrost-finance-says-hacked-funds-have-been-returned | F35: 第二来源兼资产证明
A36: 32 | B36: Sperax余额迁移漏洞/USDs | C36: 事件依据 | D36: 资产证明 | F36: 独立资产/官方证明
A37: 33 | B37: Platypus提款逻辑漏洞/USP | C37: 事件依据 | D37: 资产证明 | F37: 事件来源兼资产证明
A38: 34 | B38: Kujira抵押估值漏洞/USK | C38: 事件依据 | D38: 资产证明 | F38: 独立资产/官方证明
A39: 35 | B39: DEUS授权参数漏洞/DEI | C39: 事件依据 | D39: 资产证明 | F39: 事件来源兼资产证明
A40: 36 | B40: Palmswap资产捐赠操纵/USDP | C40: 事件依据 | D40: 资产证明 | F40: 事件来源兼资产证明
A41: 37 | B41: Raft舍入异常铸币/R | C41: 事件依据 | D41: 资产证明 | F41: 事件来源兼资产证明
A42: 38 | B42: Abracadabra债务舍入/MIM | C42: 事件依据 | D42: 资产证明 | F42: 独立资产/官方证明
A43: 39 | B43: Prisma迁移重入攻击/mkUSD | C43: 事件依据 | D43: 资产证明 | F43: 事件来源兼资产证明
A44: 40 | B44: Anzen金库精度漏洞/USDz | C44: 事件依据 | D44: 资产证明 | F44: 独立官方资产/产品证明
A45: 41 | B45: Zoth抵押计量错误/ZeUSD | C45: 事件依据 | D45: 资产证明 | F45: Zoth官方ZeUSD代币与合约说明
A46: 42 | B46: USPD初始化代理劫持/USPD | C46: 事件依据 | D46: 资产证明 | F46: 事件来源兼资产证明
A47: 43 | B47: Abracadabra偿付绕过/MIM | C47: 事件依据 | D47: 资产证明 | F47: 独立资产/官方证明
A48: 44 | B48: DEUS现货预言机操纵/DEI | C48: 事件依据 | D48: 资产证明 | E48: https://rekt.news/deus-dao-rekt | F48: 第二来源兼资产证明
A49: 45 | B49: DEUS VWAP预言机操纵/DEI | C49: 事件依据 | D49: 资产证明 | E49: https://rekt.news/deus-dao-rekt-2 | F49: 第二来源兼资产证明
A50: 46 | B50: bDollar价格操纵/BDO | C50: 事件依据 | D50: 资产证明 | F50: 事件来源兼资产证明
A51: 47 | B51: Bonq预言机操纵/BEUR | C51: 事件依据 | D51: 资产证明 | F51: 事件来源兼资产证明
A52: 48 | B52: Zunami策略估值操纵/UZD | C52: 事件依据 | D52: 资产证明 | E52: https://www.halborn.com/blog/post/explained-the-zunami-protocol-hack-august-2023 | F52: 第二来源兼资产证明
A53: 49 | B53: TheStandard抵押交换操纵/EUROs | C53: 事件依据 | D53: 资产证明 | E53: https://medium.com/thestandard-io/unity-triumphs-thestandard-io-d8beadc6a2e0 | F53: 第二来源兼资产证明
A54: 50 | B54: Resupply空金库取价/reUSD | C54: 事件依据 | D54: 资产证明 | F54: 事件来源兼资产证明
A55: 51 | B55: Money on Chain预言机故障/DOC | C55: 事件依据 | D55: 资产证明 | F55: 独立资产/官方证明
A56: 52 | B56: NuBits流动性枯竭/NBT | C56: 事件依据 | D56: 资产证明 | F56: 事件来源兼资产证明
A57: 53 | B57: Terra流动性挤兑/UST | C57: 事件依据 | D57: 资产证明 | F57: 事件来源兼资产证明
A58: 54 | B58: FDUSD储备争议脱锚/FDUSD | C58: 事件依据 | D58: 资产证明 | E58: https://www.binance.com/en/support/announcement/detail/a43abc2076b14f768669703ee5f93574 | F58: 独立资产/官方证明
A59: 55 | B59: Ethena场所价格偏离/USDe | C59: 事件依据 | D59: 资产证明 | F59: Ethena官方资产与储备说明
A60: 56 | B60: Stables Labs流动性失稳/USDX | C60: 事件依据 | D60: 资产证明 | E60: https://pharos.watch/learn/case-studies/stream-elixir-contagion-2025/ | F60: 第二来源兼资产证明
A61: 57 | B61: ESD收缩修复失效/ESD | C61: 事件依据 | D61: 资产证明 | F61: 事件来源兼资产证明
A62: 58 | B62: Fei退出惩罚失灵/FEI | C62: 事件依据 | D62: 资产证明 | F62: 事件来源兼资产证明
A63: 59 | B63: Synthetix债务回锚/sUSD | C63: 事件依据 | D63: 资产证明 | E63: https://blog.synthetix.io/synthetix-susd-peg-update/ | F63: 独立资产/官方证明
A64: 60 | B64: Iron Finance信心挤兑/IRON | C64: 事件依据 | D64: 资产证明 | F64: 事件来源兼资产证明
A65: 61 | B65: WLFI负面信息冲击与短时价格偏离/USD1 | C65: 事件依据 | D65: 资产证明 | E65: https://www.theblock.co/news/markets/2026-02-23-trump-backed-world-liberty-financial-says-usd1-short-and-social-media-attack-fails-as-stablecoin-briefly-dips-390857 https://www.chaincatcher.com/article/2247478 https://data.binance.vision/data/spot/monthly/klines/USD1USDT/1h/USD1USDT-1h-2026-02.zip | F65: 独立资产/官方证明
A66: 62 | B66: Tether金库遭窃/USDT | C66: 事件依据 | D66: 资产证明 | E66: https://tether.io/news/update-on-security-incident/ | F66: 独立资产/官方证明
A67: 63 | B67: Iron vFarm奖励配置/IRON | C67: 事件依据 | D67: 资产证明 | F67: 事件来源兼资产证明
A68: 64 | B68: CoinFLEX提现暂停/flexUSD | C68: 事件依据 | D68: 资产证明 | F68: 事件来源兼资产证明
A69: 65 | B69: Solend薄池价格操纵/USDH | C69: 事件依据 | D69: 资产证明 | E69: https://v2.solend.fi/ | F69: 事件来源兼资产证明
A70: 66 | B70: Euler攻击传染Angle/agEUR | C70: 事件依据 | D70: 资产证明 | F70: 独立资产/官方证明
A71: 67 | B71: Yearn旧iEarn配置漏洞/USDT | C71: 事件依据 | D71: 资产证明 | F71: 独立资产/官方证明
A72: 68 | B72: Elephant回购合约操纵/TRUNK·BUSD | C72: 事件依据 | D72: 资产证明 | F72: 事件来源兼资产证明
A73: 69 | B73: Seneca授权滥用/senUSD | C73: 事件依据 | D73: 资产证明 | F73: 事件来源兼资产证明
A74: 70 | B74: UwU借贷协议攻击/sUSDe | C74: 事件依据 | D74: 资产证明 | F74: 独立资产/官方证明
A75: 71 | B75: Infini残留权限提取/USDC | C75: 事件依据 | D75: 资产证明 | F75: 独立资产/官方证明
A76: 72 | B76: Zoth金库恶意升级/USD0++ | C76: 事件依据 | D76: 资产证明 | F76: 事件来源兼资产证明
A77: 73 | B77: Abracadabra GM抵押攻击/MIM | C77: 事件依据 | D77: 资产证明 | F77: 独立资产/官方证明
A78: 74 | B78: Nobitex破坏性攻击/USDT等 | C78: 事件依据 | D78: 资产证明 | F78: 事件来源兼资产证明
A79: 75 | B79: Kujira合并退出/USK | C79: 事件依据 | D79: 资产证明 | F79: 独立资产/官方证明
A80: 76 | B80: Elixir对手方传染/deUSD | C80: 事件依据 | D80: 资产证明 | F80: 事件来源兼资产证明
A81: 77 | B81: Gyroscope跨链授权/GYD | C81: 事件依据 | D81: 资产证明 | F81: 独立资产/官方证明
... A90: 86 | B90: Notional遗留合约漏洞/USDC·DAI | C90: 事件依据 | D90: 资产证明 | F90: 事件来源兼资产证明
A91: 87 | B91: 郭某钊非法换汇/USDT | C91: 事件依据 | D91: 资产证明 | E91: https://www.safe.gov.cn/safe/2023/1227/23710.html | F91: 独立资产/官方证明
A92: 88 | B92: Garantex非法结算/USDT | C92: 事件依据 | D92: 资产证明 | F92: 独立资产/官方证明
A93: 89 | B93: Huione洗钱结算/USDT | C93: 事件依据 | D93: 资产证明 | F93: 独立资产/官方证明
A94: 90 | B94: 上海地下钱庄换汇/USDT | C94: 事件依据 | D94: 资产证明 | F94: 独立资产/官方证明
A95: 91 | B95: 杀猪盘诈骗网络追缴/USDT | C95: 事件依据 | D95: 资产证明 | F95: 独立资产/官方证明
A96: 92 | B96: TGR洗钱网络制裁/USDT | C96: 事件依据 | D96: 资产证明 | F96: 独立资产/官方证明
A97: 93 | B97: Shelbit制裁规避结算/USDT | C97: 事件依据 | D97: 资产证明 | F97: 独立资产/官方证明
A98: 94 | B98: 投资诈骗团伙黄金洗钱/USDT | C98: 事件依据 | D98: 资产证明 | F98: 独立资产/官方证明
A99: 95 | B99: 台中OTC团伙暴力纠纷/USDT | C99: 事件依据 | D99: 资产证明 | E99: https://www.cna.com.tw/news/asoc/202505070082.aspx | F99: 独立资产/官方证明
A100: 96 | B100: Gotbit市场操纵所得/USDT·USDC | C100: 事件依据 | D100: 资产证明 | F100: 事件来源兼资产证明
A101: 97 | B101: Grinex制裁通道迁移/A7A5 | C101: 事件依据 | D101: 资产证明 | E101: https://www.chainalysis.com/blog/a7a5-grinex-russian-crypto-economy-ofac-sanctions-august-2025/ | F101: 第二来源兼资产证明
A102: 98 | B102: 伊朗央行大额购入/USDT | C102: 事件依据 | D102: 资产证明 | F102: 独立资产/官方证明
A103: 99 | B103: 太原诈骗团伙资金转移/USDT | C103: 事件依据 | D103: 资产证明 | F103: 独立资产/官方证明
A104: 100 | B104: 投资诈骗网络资金查扣/USDT | C104: 事件依据 | D104: 资产证明 | F104: 独立资产/官方证明
A105: 101 | B105: 香港冒牌发行人诈骗/HKDAP·HSBC | C105: 事件依据 | D105: 资产证明 | F105: 事件来源兼资产证明
A106: 102 | B106: Paxos监管停发/BUSD | C106: 事件依据 | D106: 资产证明 | F106: 事件来源兼资产证明
A107: 103 | B107: Tether旧链停止支持/USDT | C107: 事件依据 | D107: 资产证明 | F107: 独立资产/官方证明
A108: 104 | B108: Kraken欧洲交易限制/USDT等 | C108: 事件依据 | D108: 资产证明 | F108: 事件来源兼资产证明
A109: 105 | B109: Binance欧洲交易限制/多稳定币 | C109: 事件依据 | D109: 资产证明 | E109: https://www.esma.europa.eu/sites/default/files/2025-01/ESMA75-223375936-6099_Statement_on_stablecoins.pdf | F109: 第二来源兼资产证明
A110: 106 | B110: Ethena德国业务清算/USDe | C110: 事件依据 | D110: 资产证明 | F110: Ethena官方资产与储备说明
A111: 107 | B111: Circle业务钱包冻结/USDC | C111: 事件依据 | D111: 资产证明 | F111: 独立资产/官方证明
A112: 108 | B112: Tether执法协作冻结/USDT | C112: 事件依据 | D112: 资产证明 | F112: 独立资产/官方证明
